{"event_timestamp": "2026-05-11 19:54:00", "date": "2017-11-02", "team_1": "AGO", "team_2": "GODSENT", "map": "Mirage", "result_1": 16, "result_2": 13, "map_winner": 1, "rank_1": 24, "rank_2": 33, "event_id": 3251, "match_id": 2316690}
{"event_timestamp": "2026-05-11 19:54:00", "date": "2017-11-02", "team_1": "NRG", "team_2": "Complexity", "map": "Inferno", "result_1": 10, "result_2": 16, "map_winner": 2, "rank_1": 28, "rank_2": 49, "event_id": 3252, "match_id": 2316680}
{"event_timestamp": "2026-05-11 19:54:00", "date": "2017-11-02", "team_1": "NRG", "team_2": "Complexity", "map": "Cobblestone", "result_1": 14, "result_2": 16, "map_winner": 2, "rank_1": 28, "rank_2": 49, "event_id": 3252, "match_id": 2316680}
{"event_timestamp": "2026-05-11 19:54:00", "date": "2017-11-02", "team_1": "Valiance", "team_2": "Locastic", "map": "Cache", "result_1": 16, "result_2": 4, "map_winner": 1, "rank_1": 37, "rank_2": 184, "event_id": 3196, "match_id": 2316747}
{"event_timestamp": "2026-05-11 19:54:00", "date": "2017-11-02", "team_1": "Valiance", "team_2": "Locastic", "map": "Mirage", "result_1": 16, "result_2": 13, "map_winner": 1, "rank_1": 37, "rank_2": 184, "event_id": 3196, "match_id": 2316747}
{"event_timestamp": "2026-05-11 19:54:00", "date": "2017-11-02", "team_1": "NiP", "team_2": "G2", "map": "Overpass", "result_1": 16, "result_2": 5, "map_winner": 1, "rank_1": 9, "rank_2": 3, "event_id": 3059, "match_id": 2316597}
{"event_timestamp": "2026-05-11 19:54:00", "date": "2017-11-02", "team_1": "Tricked", "team_2": "TEAM5", "map": "Mirage", "result_1": 11, "result_2": 16, "map_winner": 2, "rank_1": 34, "rank_2": 66, "event_id": 3228, "match_id": 2316532}
{"event_timestamp": "2026-05-11 19:54:00", "date": "2017-11-02", "team_1": "TeamOne", "team_2": "Complexity", "map": "Train", "result_1": 12, "result_2": 16, "map_winner": 2, "rank_1": 81, "rank_2": 49, "event_id": 3252, "match_id": 2316679}
{"event_timestamp": "2026-05-11 19:54:00", "date": "2017-11-02", "team_1": "Nexus", "team_2": "Crowns", "map": "Cache", "result_1": 16, "result_2": 7, "map_winner": 1, "rank_1": 74, "rank_2": 102, "event_id": 3047, "match_id": 2316727}
{"event_timestamp": "2026-05-11 19:54:00", "date": "2017-11-02", "team_1": "G2", "team_2": "NiP", "map": "Cobblestone", "result_1": 8, "result_2": 16, "map_winner": 2, "rank_1": 3, "rank_2": 9, "event_id": 3059, "match_id": 2316596}
{"event_timestamp": "2026-05-11 19:54:00", "date": "2017-11-02", "team_1": "Space Jam", "team_2": "TEAM5", "map": "Train", "result_1": 16, "result_2": 19, "map_winner": 2, "rank_1": 229, "rank_2": 66, "event_id": 3320, "match_id": 2316729}
{"event_timestamp": "2026-05-11 19:54:00", "date": "2017-11-02", "team_1": "Gambit", "team_2": "Singularity", "map": "Mirage", "result_1": 17, "result_2": 19, "map_winner": 2, "rank_1": 10, "rank_2": 45, "event_id": 3047, "match_id": 2316725}
{"event_timestamp": "2026-05-11 19:54:00", "date": "2017-11-02", "team_1": "proWince", "team_2": "Zonic", "map": "Cobblestone", "result_1": 10, "result_2": 16, "map_winner": 2, "rank_1": 175, "rank_2": 196, "event_id": 3196, "match_id": 2316717}
{"event_timestamp": "2026-05-11 19:54:00", "date": "2017-11-02", "team_1": "proWince", "team_2": "Zonic", "map": "Inferno", "result_1": 9, "result_2": 16, "map_winner": 2, "rank_1": 175, "rank_2": 196, "event_id": 3196, "match_id": 2316717}
{"event_timestamp": "2026-05-11 19:54:00", "date": "2017-11-02", "team_1": "TeamOne", "team_2": "Complexity", "map": "Nuke", "result_1": 10, "result_2": 16, "map_winner": 2, "rank_1": 81, "rank_2": 49, "event_id": 3252, "match_id": 2316679}
{"event_timestamp": "2026-05-11 19:54:00", "date": "2017-11-02", "team_1": "Endpoint", "team_2": "Kinguin", "map": "Mirage", "result_1": 5, "result_2": 16, "map_winner": 2, "rank_1": 86, "rank_2": 29, "event_id": 3047, "match_id": 2316759}
{"event_timestamp": "2026-05-11 19:54:00", "date": "2017-11-02", "team_1": "Kinguin", "team_2": "Seed", "map": "Cache", "result_1": 6, "result_2": 16, "map_winner": 2, "rank_1": 29, "rank_2": 31, "event_id": 3047, "match_id": 2316720}
{"event_timestamp": "2026-05-11 19:54:00", "date": "2017-11-02", "team_1": "NRG", "team_2": "Complexity", "map": "Mirage", "result_1": 16, "result_2": 11, "map_winner": 1, "rank_1": 28, "rank_2": 49, "event_id": 3252, "match_id": 2316680}
{"event_timestamp": "2026-05-11 19:54:00", "date": "2017-11-02", "team_1": "aAa", "team_2": "ARES", "map": "Inferno", "result_1": 15, "result_2": 15, "map_winner": 2, "rank_1": 64, "rank_2": 108, "event_id": 3232, "match_id": 2316741}
{"event_timestamp": "2026-05-11 19:54:00", "date": "2017-11-02", "team_1": "NRG", "team_2": "Complexity", "map": "Mirage", "result_1": 19, "result_2": 17, "map_winner": 1, "rank_1": 28, "rank_2": 49, "event_id": 3252, "match_id": 2316613}
{"event_timestamp": "2026-05-11 19:54:00", "date": "2017-11-02", "team_1": "ARES", "team_2": "aAa", "map": "Nuke", "result_1": 5, "result_2": 16, "map_winner": 2, "rank_1": 108, "rank_2": 64, "event_id": 3232, "match_id": 2316742}
{"event_timestamp": "2026-05-11 19:54:00", "date": "2017-11-02", "team_1": "LDLC", "team_2": "BIG", "map": "Cobblestone", "result_1": 16, "result_2": 8, "map_winner": 1, "rank_1": 23, "rank_2": 17, "event_id": 3232, "match_id": 2316740}
{"event_timestamp": "2026-05-11 19:54:00", "date": "2017-11-02", "team_1": "ALTERNATE aTTaX", "team_2": "Nexus", "map": "Cobblestone", "result_1": 16, "result_2": 7, "map_winner": 1, "rank_1": 70, "rank_2": 74, "event_id": 3047, "match_id": 2316719}
{"event_timestamp": "2026-05-11 19:54:00", "date": "2017-11-02", "team_1": "Liquid", "team_2": "NRG", "map": "Inferno", "result_1": 16, "result_2": 5, "map_winner": 1, "rank_1": 8, "rank_2": 28, "event_id": 3252, "match_id": 2316678}
{"event_timestamp": "2026-05-11 19:54:00", "date": "2017-11-02", "team_1": "Gambit", "team_2": "ALTERNATE aTTaX", "map": "Train", "result_1": 11, "result_2": 16, "map_winner": 2, "rank_1": 10, "rank_2": 70, "event_id": 3047, "match_id": 2316721}
{"event_timestamp": "2026-05-11 19:54:00", "date": "2017-11-02", "team_1": "Singularity", "team_2": "Seed", "map": "Cobblestone", "result_1": 16, "result_2": 10, "map_winner": 1, "rank_1": 45, "rank_2": 31, "event_id": 3047, "match_id": 2316722}
{"event_timestamp": "2026-05-11 19:54:00", "date": "2017-11-02", "team_1": "EPG", "team_2": "GameAgents", "map": "Cache", "result_1": 16, "result_2": 13, "map_winner": 1, "rank_1": 104, "rank_2": 111, "event_id": 3320, "match_id": 2316730}
{"event_timestamp": "2026-05-11 19:54:00", "date": "2017-11-02", "team_1": "North Academy", "team_2": "Valiance", "map": "Train", "result_1": 16, "result_2": 2, "map_winner": 1, "rank_1": 47, "rank_2": 37, "event_id": 3228, "match_id": 2316531}
{"event_timestamp": "2026-05-11 19:54:00", "date": "2017-11-02", "team_1": "BIG", "team_2": "LDLC", "map": "Overpass", "result_1": 2, "result_2": 16, "map_winner": 2, "rank_1": 17, "rank_2": 23, "event_id": 3232, "match_id": 2316739}
{"event_timestamp": "2026-05-11 19:54:00", "date": "2017-11-01", "team_1": "passions", "team_2": "NOVA", "map": "Mirage", "result_1": 16, "result_2": 11, "map_winner": 1, "rank_1": 123, "rank_2": 181, "event_id": 3311, "match_id": 2316632}
{"event_timestamp": "2026-05-11 19:54:00", "date": "2017-11-01", "team_1": "Grayhound", "team_2": "SIN", "map": "Overpass", "result_1": 16, "result_2": 9, "map_winner": 1, "rank_1": 59, "rank_2": 165, "event_id": 3049, "match_id": 2316627}
{"event_timestamp": "2026-05-11 19:54:00", "date": "2017-11-01", "team_1": "Endpoint", "team_2": "Seed", "map": "Mirage", "result_1": 6, "result_2": 16, "map_winner": 2, "rank_1": 86, "rank_2": 31, "event_id": 3047, "match_id": 2316634}
{"event_timestamp": "2026-05-11 19:54:00", "date": "2017-11-01", "team_1": "Gambit", "team_2": "Nexus", "map": "Mirage", "result_1": 16, "result_2": 6, "map_winner": 1, "rank_1": 10, "rank_2": 74, "event_id": 3047, "match_id": 2316635}
{"event_timestamp": "2026-05-11 19:54:00", "date": "2017-11-01", "team_1": "TEAM5", "team_2": "NOVA", "map": "Inferno", "result_1": 16, "result_2": 12, "map_winner": 1, "rank_1": 66, "rank_2": 181, "event_id": 3311, "match_id": 2316631}
{"event_timestamp": "2026-05-11 19:54:00", "date": "2017-11-01", "team_1": "Singularity", "team_2": "Seed", "map": "Inferno", "result_1": 14, "result_2": 16, "map_winner": 2, "rank_1": 45, "rank_2": 31, "event_id": 3208, "match_id": 2316543}
{"event_timestamp": "2026-05-11 19:54:00", "date": "2017-11-01", "team_1": "Singularity", "team_2": "Seed", "map": "Cache", "result_1": 16, "result_2": 8, "map_winner": 1, "rank_1": 45, "rank_2": 31, "event_id": 3208, "match_id": 2316543}
{"event_timestamp": "2026-05-11 19:54:00", "date": "2017-11-01", "team_1": "Singularity", "team_2": "Seed", "map": "Train", "result_1": 6, "result_2": 16, "map_winner": 2, "rank_1": 45, "rank_2": 31, "event_id": 3208, "match_id": 2316543}
{"event_timestamp": "2026-05-11 19:54:00", "date": "2017-11-01", "team_1": "Gale Force", "team_2": "GX", "map": "Mirage", "result_1": 16, "result_2": 9, "map_winner": 1, "rank_1": 57, "rank_2": 90, "event_id": 3048, "match_id": 2316460}
{"event_timestamp": "2026-05-11 19:54:00", "date": "2017-11-01", "team_1": "Masterminds", "team_2": "Noxide", "map": "Cobblestone", "result_1": 16, "result_2": 11, "map_winner": 1, "rank_1": 244, "rank_2": 180, "event_id": 3049, "match_id": 2316629}
{"event_timestamp": "2026-05-11 19:54:00", "date": "2017-11-01", "team_1": "CLG Academy", "team_2": "Naventic", "map": "Cobblestone", "result_1": 5, "result_2": 16, "map_winner": 2, "rank_1": 107, "rank_2": 109, "event_id": 3048, "match_id": 2316462}
{"event_timestamp": "2026-05-11 19:54:00", "date": "2017-11-01", "team_1": "Morior Invictus", "team_2": "Adaptation", "map": "Cobblestone", "result_1": 16, "result_2": 12, "map_winner": 1, "rank_1": 147, "rank_2": 135, "event_id": 3048, "match_id": 2316607}
{"event_timestamp": "2026-05-11 19:54:00", "date": "2017-11-01", "team_1": "SoaR", "team_2": "Mythic", "map": "Inferno", "result_1": 16, "result_2": 8, "map_winner": 1, "rank_1": 69, "rank_2": 67, "event_id": 3048, "match_id": 2316461}
{"event_timestamp": "2026-05-11 19:54:00", "date": "2017-11-01", "team_1": "Luminosity", "team_2": "SK", "map": "Inferno", "result_1": 16, "result_2": 14, "map_winner": 1, "rank_1": 21, "rank_2": 1, "event_id": 3060, "match_id": 2316500}
{"event_timestamp": "2026-05-11 19:54:00", "date": "2017-11-01", "team_1": "SK", "team_2": "Luminosity", "map": "Train", "result_1": 16, "result_2": 13, "map_winner": 1, "rank_1": 1, "rank_2": 21, "event_id": 3060, "match_id": 2316499}
{"event_timestamp": "2026-05-11 19:54:00", "date": "2017-11-01", "team_1": "Cloud9", "team_2": "SK", "map": "Mirage", "result_1": 16, "result_2": 2, "map_winner": 1, "rank_1": 7, "rank_2": 1, "event_id": 3060, "match_id": 2316498}
{"event_timestamp": "2026-05-11 19:54:00", "date": "2017-11-01", "team_1": "fnatic", "team_2": "G2", "map": "Inferno", "result_1": 16, "result_2": 12, "map_winner": 1, "rank_1": 12, "rank_2": 3, "event_id": 3059, "match_id": 2316590}
{"event_timestamp": "2026-05-11 19:54:00", "date": "2017-11-01", "team_1": "ALTERNATE aTTaX", "team_2": "Seed", "map": "Overpass", "result_1": 16, "result_2": 10, "map_winner": 1, "rank_1": 70, "rank_2": 31, "event_id": 3047, "match_id": 2316636}
{"event_timestamp": "2026-05-11 19:54:00", "date": "2017-11-01", "team_1": "Endpoint", "team_2": "Nexus", "map": "Mirage", "result_1": 16, "result_2": 14, "map_winner": 1, "rank_1": 86, "rank_2": 74, "event_id": 3047, "match_id": 2316640}
{"event_timestamp": "2026-05-11 19:54:00", "date": "2017-11-01", "team_1": "Gambit", "team_2": "Fragsters", "map": "Cache", "result_1": 16, "result_2": 4, "map_winner": 1, "rank_1": 10, "rank_2": 44, "event_id": 3047, "match_id": 2316638}
{"event_timestamp": "2026-05-11 19:54:00", "date": "2017-11-01", "team_1": "Astralis", "team_2": "mousesports", "map": "Inferno", "result_1": 16, "result_2": 14, "map_winner": 1, "rank_1": 4, "rank_2": 11, "event_id": 3059, "match_id": 2316592}
{"event_timestamp": "2026-05-11 19:54:00", "date": "2017-11-01", "team_1": "mousesports", "team_2": "Astralis", "map": "Mirage", "result_1": 25, "result_2": 22, "map_winner": 1, "rank_1": 11, "rank_2": 4, "event_id": 3059, "match_id": 2316593}
{"event_timestamp": "2026-05-11 19:54:00", "date": "2017-11-01", "team_1": "Valiance", "team_2": "Tricked", "map": "Cobblestone", "result_1": 16, "result_2": 12, "map_winner": 1, "rank_1": 37, "rank_2": 34, "event_id": 3293, "match_id": 2316714}
{"event_timestamp": "2026-05-11 19:54:00", "date": "2017-11-01", "team_1": "Spirit Academy", "team_2": "eSuba", "map": "Mirage", "result_1": 16, "result_2": 10, "map_winner": 1, "rank_1": 87, "rank_2": 120, "event_id": 3320, "match_id": 2316546}
{"event_timestamp": "2026-05-11 19:54:00", "date": "2017-11-01", "team_1": "Valiance", "team_2": "Tricked", "map": "Mirage", "result_1": 16, "result_2": 8, "map_winner": 1, "rank_1": 37, "rank_2": 34, "event_id": 3293, "match_id": 2316714}
{"event_timestamp": "2026-05-11 19:54:00", "date": "2017-11-01", "team_1": "RESISTANCE", "team_2": "Ripple", "map": "Overpass", "result_1": 16, "result_2": 11, "map_winner": 1, "rank_1": 138, "rank_2": 218, "event_id": 3196, "match_id": 2316600}
{"event_timestamp": "2026-05-11 19:54:00", "date": "2017-11-01", "team_1": "RESISTANCE", "team_2": "Ripple", "map": "Nuke", "result_1": 16, "result_2": 8, "map_winner": 1, "rank_1": 138, "rank_2": 218, "event_id": 3196, "match_id": 2316600}
{"event_timestamp": "2026-05-11 19:54:00", "date": "2017-11-01", "team_1": "Crowns", "team_2": "Not Academy", "map": "Mirage", "result_1": 11, "result_2": 16, "map_winner": 2, "rank_1": 102, "rank_2": 77, "event_id": 3047, "match_id": 2316606}
{"event_timestamp": "2026-05-11 19:54:00", "date": "2017-11-01", "team_1": "Valiance", "team_2": "Tricked", "map": "Train", "result_1": 11, "result_2": 16, "map_winner": 2, "rank_1": 37, "rank_2": 34, "event_id": 3293, "match_id": 2316714}
{"event_timestamp": "2026-05-11 19:54:00", "date": "2017-11-01", "team_1": "ALTERNATE aTTaX", "team_2": "Not Academy", "map": "Train", "result_1": 13, "result_2": 16, "map_winner": 2, "rank_1": 70, "rank_2": 77, "event_id": 3047, "match_id": 2316639}
{"event_timestamp": "2026-05-11 19:54:00", "date": "2017-11-01", "team_1": "Natus Vincere", "team_2": "Space Soldiers", "map": "Train", "result_1": 9, "result_2": 16, "map_winner": 2, "rank_1": 15, "rank_2": 20, "event_id": 3122, "match_id": 2316641}
{"event_timestamp": "2026-05-11 19:54:00", "date": "2017-11-01", "team_1": "Natus Vincere", "team_2": "Space Soldiers", "map": "Overpass", "result_1": 19, "result_2": 17, "map_winner": 1, "rank_1": 15, "rank_2": 20, "event_id": 3122, "match_id": 2316641}
{"event_timestamp": "2026-05-11 19:54:00", "date": "2017-11-01", "team_1": "passions", "team_2": "SEAL", "map": "Overpass", "result_1": 16, "result_2": 9, "map_winner": 1, "rank_1": 123, "rank_2": 259, "event_id": 3320, "match_id": 2316545}
{"event_timestamp": "2026-05-11 19:54:00", "date": "2017-11-01", "team_1": "G2", "team_2": "fnatic", "map": "Cobblestone", "result_1": 16, "result_2": 13, "map_winner": 1, "rank_1": 3, "rank_2": 12, "event_id": 3059, "match_id": 2316591}
{"event_timestamp": "2026-05-11 19:54:00", "date": "2017-11-01", "team_1": "WASD", "team_2": "RESISTANCE", "map": "Inferno", "result_1": 16, "result_2": 7, "map_winner": 1, "rank_1": 105, "rank_2": 138, "event_id": 3311, "match_id": 2316633}
{"event_timestamp": "2026-05-11 19:54:00", "date": "2017-11-01", "team_1": "TEAM5", "team_2": "Not Academy", "map": "Cache", "result_1": 11, "result_2": 16, "map_winner": 2, "rank_1": 66, "rank_2": 77, "event_id": 3047, "match_id": 2316728}
{"event_timestamp": "2026-05-11 19:54:00", "date": "2017-11-01", "team_1": "Natus Vincere", "team_2": "Space Soldiers", "map": "Cobblestone", "result_1": 16, "result_2": 14, "map_winner": 1, "rank_1": 15, "rank_2": 20, "event_id": 3122, "match_id": 2316641}
{"event_timestamp": "2026-05-11 19:54:00", "date": "2017-10-31", "team_1": "Noxide", "team_2": "SIN", "map": "Cache", "result_1": 5, "result_2": 16, "map_winner": 2, "rank_1": 180, "rank_2": 165, "event_id": 3049, "match_id": 2316322}
{"event_timestamp": "2026-05-11 19:54:00", "date": "2017-10-31", "team_1": "TEAM5", "team_2": "Endpoint", "map": "Inferno", "result_1": 9, "result_2": 16, "map_winner": 2, "rank_1": 66, "rank_2": 86, "event_id": 3047, "match_id": 2316602}
{"event_timestamp": "2026-05-11 19:54:00", "date": "2017-10-31", "team_1": "INFURITY", "team_2": "NYYRIKKI", "map": "Mirage", "result_1": 4, "result_2": 16, "map_winner": 2, "rank_1": 276, "rank_2": 200, "event_id": 3276, "match_id": 2316646}
{"event_timestamp": "2026-05-11 19:54:00", "date": "2017-10-31", "team_1": "Singularity", "team_2": "ALTERNATE aTTaX", "map": "Cobblestone", "result_1": 11, "result_2": 16, "map_winner": 2, "rank_1": 45, "rank_2": 70, "event_id": 3293, "match_id": 2316568}
{"event_timestamp": "2026-05-11 19:54:00", "date": "2017-10-31", "team_1": "Kinguin", "team_2": "SEAL", "map": "Overpass", "result_1": 16, "result_2": 10, "map_winner": 1, "rank_1": 29, "rank_2": 259, "event_id": 3290, "match_id": 2316351}
{"event_timestamp": "2026-05-11 19:54:00", "date": "2017-10-31", "team_1": "SYF", "team_2": "Conspiracy", "map": "Cache", "result_1": 16, "result_2": 9, "map_winner": 1, "rank_1": 204, "rank_2": 269, "event_id": 3049, "match_id": 2316628}
{"event_timestamp": "2026-05-11 19:54:00", "date": "2017-10-31", "team_1": "Rise Nation", "team_2": "Gale Force", "map": "Inferno", "result_1": 16, "result_2": 13, "map_winner": 1, "rank_1": 42, "rank_2": 57, "event_id": 3048, "match_id": 2316459}
{"event_timestamp": "2026-05-11 19:54:00", "date": "2017-10-31", "team_1": "seadoggs", "team_2": "Conspiracy", "map": "Cache", "result_1": 12, "result_2": 16, "map_winner": 2, "rank_1": 170, "rank_2": 269, "event_id": 3049, "match_id": 2316558}
{"event_timestamp": "2026-05-11 19:54:00", "date": "2017-10-31", "team_1": "Corvidae", "team_2": "Riotous", "map": "Train", "result_1": 16, "result_2": 6, "map_winner": 1, "rank_1": 209, "rank_2": 178, "event_id": 3049, "match_id": 2316626}
{"event_timestamp": "2026-05-11 19:54:00", "date": "2017-10-31", "team_1": "Chiefs", "team_2": "Athletico", "map": "Cache", "result_1": 16, "result_2": 8, "map_winner": 1, "rank_1": 73, "rank_2": 95, "event_id": 3049, "match_id": 2316625}
{"event_timestamp": "2026-05-11 19:54:00", "date": "2017-10-31", "team_1": "SoaR", "team_2": "Morior Invictus", "map": "Mirage", "result_1": 16, "result_2": 14, "map_winner": 1, "rank_1": 69, "rank_2": 147, "event_id": 3048, "match_id": 2316392}
{"event_timestamp": "2026-05-11 19:54:00", "date": "2017-10-31", "team_1": "Epsilon", "team_2": "CHAOS", "map": "Mirage", "result_1": 16, "result_2": 12, "map_winner": 1, "rank_1": 71, "rank_2": 103, "event_id": 3047, "match_id": 2316601}
{"event_timestamp": "2026-05-11 19:54:00", "date": "2017-10-31", "team_1": "G2", "team_2": "mousesports", "map": "Cobblestone", "result_1": 14, "result_2": 16, "map_winner": 2, "rank_1": 3, "rank_2": 11, "event_id": 3059, "match_id": 2316586}
{"event_timestamp": "2026-05-11 19:54:00", "date": "2017-10-31", "team_1": "Astralis", "team_2": "fnatic", "map": "Mirage", "result_1": 16, "result_2": 10, "map_winner": 1, "rank_1": 4, "rank_2": 12, "event_id": 3059, "match_id": 2316589}
{"event_timestamp": "2026-05-11 19:54:00", "date": "2017-10-31", "team_1": "Tricked", "team_2": "ALTERNATE aTTaX", "map": "Overpass", "result_1": 16, "result_2": 11, "map_winner": 1, "rank_1": 34, "rank_2": 70, "event_id": 3293, "match_id": 2316569}
{"event_timestamp": "2026-05-11 19:54:00", "date": "2017-10-31", "team_1": "KlikTech", "team_2": "Squared", "map": "Overpass", "result_1": 16, "result_2": 4, "map_winner": 1, "rank_1": 164, "rank_2": 163, "event_id": 3196, "match_id": 2316598}
{"event_timestamp": "2026-05-11 19:54:00", "date": "2017-10-31", "team_1": "SK", "team_2": "Cloud9", "map": "Cobblestone", "result_1": 14, "result_2": 16, "map_winner": 2, "rank_1": 1, "rank_2": 7, "event_id": 3060, "match_id": 2316497}
{"event_timestamp": "2026-05-11 19:54:00", "date": "2017-10-31", "team_1": "SJ", "team_2": "Crowns", "map": "Inferno", "result_1": 16, "result_2": 9, "map_winner": 1, "rank_1": 84, "rank_2": 102, "event_id": 3047, "match_id": 2316605}
{"event_timestamp": "2026-05-11 19:54:00", "date": "2017-10-31", "team_1": "exceL", "team_2": "EURONICS", "map": "Inferno", "result_1": 16, "result_2": 8, "map_winner": 1, "rank_1": 142, "rank_2": 85, "event_id": 3320, "match_id": 2316544}
{"event_timestamp": "2026-05-11 19:54:00", "date": "2017-10-31", "team_1": "fnatic", "team_2": "Astralis", "map": "Train", "result_1": 16, "result_2": 8, "map_winner": 1, "rank_1": 12, "rank_2": 4, "event_id": 3059, "match_id": 2316588}
{"event_timestamp": "2026-05-11 19:54:00", "date": "2017-10-31", "team_1": "Gambit", "team_2": "TEAM5", "map": "Train", "result_1": 16, "result_2": 4, "map_winner": 1, "rank_1": 10, "rank_2": 66, "event_id": 3047, "match_id": 2315517}
{"event_timestamp": "2026-05-11 19:54:00", "date": "2017-10-31", "team_1": "KlikTech", "team_2": "Squared", "map": "Inferno", "result_1": 16, "result_2": 5, "map_winner": 1, "rank_1": 164, "rank_2": 163, "event_id": 3196, "match_id": 2316598}
{"event_timestamp": "2026-05-11 19:54:00", "date": "2017-10-31", "team_1": "Epsilon", "team_2": "Invictus Aquilas", "map": "Mirage", "result_1": 16, "result_2": 7, "map_winner": 1, "rank_1": 71, "rank_2": 127, "event_id": 3047, "match_id": 2316603}
{"event_timestamp": "2026-05-11 19:54:00", "date": "2017-10-31", "team_1": "NYYRIKKI", "team_2": "Acapella", "map": "Cache", "result_1": 12, "result_2": 16, "map_winner": 2, "rank_1": 200, "rank_2": 197, "event_id": 3276, "match_id": 2316651}
{"event_timestamp": "2026-05-11 19:54:00", "date": "2017-10-31", "team_1": "hASSeLsNOk", "team_2": "INFURITY", "map": "Mirage", "result_1": 16, "result_2": 5, "map_winner": 1, "rank_1": 141, "rank_2": 276, "event_id": 3276, "match_id": 2316652}
{"event_timestamp": "2026-05-11 19:54:00", "date": "2017-10-31", "team_1": "mousesports", "team_2": "G2", "map": "Inferno", "result_1": 9, "result_2": 16, "map_winner": 2, "rank_1": 11, "rank_2": 3, "event_id": 3059, "match_id": 2316587}
{"event_timestamp": "2026-05-11 19:54:00", "date": "2017-10-30", "team_1": "CLG", "team_2": "Luminosity", "map": "Cache", "result_1": 3, "result_2": 16, "map_winner": 2, "rank_1": 19, "rank_2": 21, "event_id": 2938, "match_id": 2316535}
{"event_timestamp": "2026-05-11 19:54:00", "date": "2017-10-30", "team_1": "Singularity", "team_2": "NOVA", "map": "Mirage", "result_1": 16, "result_2": 9, "map_winner": 1, "rank_1": 47, "rank_2": 203, "event_id": 3320, "match_id": 2316547}
{"event_timestamp": "2026-05-11 19:54:00", "date": "2017-10-30", "team_1": "Masterminds", "team_2": "AVANT", "map": "Mirage", "result_1": 7, "result_2": 16, "map_winner": 2, "rank_1": 245, "rank_2": 224, "event_id": 3049, "match_id": 2316560}
{"event_timestamp": "2026-05-11 19:54:00", "date": "2017-10-30", "team_1": "Noxide", "team_2": "AVANT", "map": "Cobblestone", "result_1": 7, "result_2": 16, "map_winner": 2, "rank_1": 179, "rank_2": 224, "event_id": 3049, "match_id": 2316559}
{"event_timestamp": "2026-05-11 19:54:00", "date": "2017-10-30", "team_1": "Misfits", "team_2": "Complexity", "map": "Inferno", "result_1": 7, "result_2": 16, "map_winner": 2, "rank_1": 25, "rank_2": 44, "event_id": 2938, "match_id": 2316557}
{"event_timestamp": "2026-05-11 19:54:00", "date": "2017-10-30", "team_1": "Misfits", "team_2": "Complexity", "map": "Mirage", "result_1": 14, "result_2": 16, "map_winner": 2, "rank_1": 25, "rank_2": 44, "event_id": 2938, "match_id": 2316557}
{"event_timestamp": "2026-05-11 19:54:00", "date": "2017-10-30", "team_1": "CLG", "team_2": "Luminosity", "map": "Overpass", "result_1": 7, "result_2": 16, "map_winner": 2, "rank_1": 19, "rank_2": 21, "event_id": 2938, "match_id": 2316535}
{"event_timestamp": "2026-05-11 19:54:00", "date": "2017-10-30", "team_1": "CLG", "team_2": "Luminosity", "map": "Cobblestone", "result_1": 16, "result_2": 4, "map_winner": 1, "rank_1": 19, "rank_2": 21, "event_id": 2938, "match_id": 2316535}
{"event_timestamp": "2026-05-11 19:54:00", "date": "2017-10-30", "team_1": "Ghost", "team_2": "Cloud9", "map": "Cobblestone", "result_1": 7, "result_2": 16, "map_winner": 2, "rank_1": 59, "rank_2": 6, "event_id": 3060, "match_id": 2316496}
{"event_timestamp": "2026-05-11 19:54:00", "date": "2017-10-30", "team_1": "Cloud9", "team_2": "Ghost", "map": "Inferno", "result_1": 16, "result_2": 12, "map_winner": 1, "rank_1": 6, "rank_2": 59, "event_id": 3060, "match_id": 2316495}
{"event_timestamp": "2026-05-11 19:54:00", "date": "2017-10-30", "team_1": "CLG", "team_2": "Immortals", "map": "Train", "result_1": 16, "result_2": 12, "map_winner": 1, "rank_1": 19, "rank_2": 51, "event_id": 3060, "match_id": 2316494}
{"event_timestamp": "2026-05-11 19:54:00", "date": "2017-10-30", "team_1": "PRIDE", "team_2": "Tricked", "map": "Cobblestone", "result_1": 7, "result_2": 16, "map_winner": 2, "rank_1": 39, "rank_2": 35, "event_id": 3311, "match_id": 2316542}
{"event_timestamp": "2026-05-11 19:54:00", "date": "2017-10-30", "team_1": "ex-Outlaws", "team_2": "ALTERNATE aTTaX", "map": "Train", "result_1": 16, "result_2": 19, "map_winner": 2, "rank_1": 38, "rank_2": 78, "event_id": 3290, "match_id": 2316349}
{"event_timestamp": "2026-05-11 19:54:00", "date": "2017-10-30", "team_1": "Misfits", "team_2": "Complexity", "map": "Nuke", "result_1": 19, "result_2": 15, "map_winner": 1, "rank_1": 25, "rank_2": 44, "event_id": 2938, "match_id": 2316557}
{"event_timestamp": "2026-05-11 19:54:00", "date": "2017-10-30", "team_1": "TEAM5", "team_2": "Nexus", "map": "Cache", "result_1": 16, "result_2": 14, "map_winner": 1, "rank_1": 77, "rank_2": 80, "event_id": 3047, "match_id": 2316389}
{"event_timestamp": "2026-05-11 19:54:00", "date": "2017-10-30", "team_1": "Epsilon", "team_2": "Seed", "map": "Overpass", "result_1": 8, "result_2": 16, "map_winner": 2, "rank_1": 65, "rank_2": 28, "event_id": 3311, "match_id": 2316540}
{"event_timestamp": "2026-05-11 19:54:00", "date": "2017-10-30", "team_1": "ALTERNATE aTTaX", "team_2": "EnVyUs Academy", "map": "Cache", "result_1": 16, "result_2": 13, "map_winner": 1, "rank_1": 70, "rank_2": 75, "event_id": 3305, "match_id": 2316488}
{"event_timestamp": "2026-05-11 19:54:00", "date": "2017-10-30", "team_1": "Kinguin", "team_2": "Red Reserve", "map": "Cobblestone", "result_1": 16, "result_2": 11, "map_winner": 1, "rank_1": 33, "rank_2": 52, "event_id": 3047, "match_id": 2316537}
{"event_timestamp": "2026-05-11 19:54:00", "date": "2017-10-30", "team_1": "ALTERNATE aTTaX", "team_2": "EnVyUs Academy", "map": "Cobblestone", "result_1": 11, "result_2": 16, "map_winner": 2, "rank_1": 70, "rank_2": 75, "event_id": 3305, "match_id": 2316488}
{"event_timestamp": "2026-05-11 19:54:00", "date": "2017-10-30", "team_1": "Nexus", "team_2": "aAa", "map": "Cache", "result_1": 16, "result_2": 11, "map_winner": 1, "rank_1": 74, "rank_2": 64, "event_id": 3047, "match_id": 2316539}
{"event_timestamp": "2026-05-11 19:54:00", "date": "2017-10-30", "team_1": "TEAM5", "team_2": "passions", "map": "Train", "result_1": 16, "result_2": 12, "map_winner": 1, "rank_1": 66, "rank_2": 123, "event_id": 3311, "match_id": 2316541}
{"event_timestamp": "2026-05-11 19:54:00", "date": "2017-10-30", "team_1": "ALTERNATE aTTaX", "team_2": "EnVyUs Academy", "map": "Train", "result_1": 14, "result_2": 16, "map_winner": 2, "rank_1": 70, "rank_2": 75, "event_id": 3305, "match_id": 2316488}
{"event_timestamp": "2026-05-11 19:54:00", "date": "2017-10-30", "team_1": "Fragsters", "team_2": "iGame.com", "map": "Mirage", "result_1": 9, "result_2": 16, "map_winner": 2, "rank_1": 46, "rank_2": 111, "event_id": 3047, "match_id": 2316538}
{"event_timestamp": "2026-05-11 19:54:00", "date": "2017-10-30", "team_1": "EnVyUs Academy", "team_2": "eSuba", "map": "Cache", "result_1": 16, "result_2": 11, "map_winner": 1, "rank_1": 62, "rank_2": 128, "event_id": 3305, "match_id": 2316391}
{"event_timestamp": "2026-05-11 19:54:00", "date": "2017-10-30", "team_1": "EnVyUs Academy", "team_2": "eSuba", "map": "Nuke", "result_1": 16, "result_2": 9, "map_winner": 1, "rank_1": 62, "rank_2": 128, "event_id": 3305, "match_id": 2316391}
{"event_timestamp": "2026-05-11 19:54:00", "date": "2017-10-30", "team_1": "Red Reserve", "team_2": "Nexus", "map": "Cobblestone", "result_1": 11, "result_2": 16, "map_winner": 2, "rank_1": 52, "rank_2": 80, "event_id": 3047, "match_id": 2316360}
{"event_timestamp": "2026-05-11 19:54:00", "date": "2017-10-30", "team_1": "aAa", "team_2": "SJ", "map": "Overpass", "result_1": 16, "result_2": 9, "map_winner": 1, "rank_1": 75, "rank_2": 83, "event_id": 3290, "match_id": 2316350}
{"event_timestamp": "2026-05-11 19:54:00", "date": "2017-10-29", "team_1": "Astralis", "team_2": "G2", "map": "Nuke", "result_1": 16, "result_2": 14, "map_winner": 1, "rank_1": 2, "rank_2": 5, "event_id": 3133, "match_id": 2316477}
{"event_timestamp": "2026-05-11 19:54:00", "date": "2017-10-29", "team_1": "Grayhound", "team_2": "5POWER", "map": "Inferno", "result_1": 10, "result_2": 16, "map_winner": 2, "rank_1": 54, "rank_2": 108, "event_id": 3240, "match_id": 2316515}
{"event_timestamp": "2026-05-11 19:54:00", "date": "2017-10-29", "team_1": "Astralis", "team_2": "G2", "map": "Mirage", "result_1": 14, "result_2": 16, "map_winner": 2, "rank_1": 2, "rank_2": 5, "event_id": 3133, "match_id": 2316477}
{"event_timestamp": "2026-05-11 19:54:00", "date": "2017-10-29", "team_1": "Astralis", "team_2": "G2", "map": "Inferno", "result_1": 11, "result_2": 16, "map_winner": 2, "rank_1": 2, "rank_2": 5, "event_id": 3133, "match_id": 2316477}
{"event_timestamp": "2026-05-11 19:54:00", "date": "2017-10-29", "team_1": "Renegades", "team_2": "TYLOO", "map": "Cache", "result_1": 16, "result_2": 14, "map_winner": 1, "rank_1": 18, "rank_2": 87, "event_id": 3249, "match_id": 2316508}
{"event_timestamp": "2026-05-11 19:54:00", "date": "2017-10-29", "team_1": "Renegades", "team_2": "TYLOO", "map": "Train", "result_1": 16, "result_2": 12, "map_winner": 1, "rank_1": 18, "rank_2": 87, "event_id": 3249, "match_id": 2316508}
{"event_timestamp": "2026-05-11 19:54:00", "date": "2017-10-29", "team_1": "pro100", "team_2": "Spirit", "map": "Overpass", "result_1": 5, "result_2": 16, "map_winner": 2, "rank_1": 69, "rank_2": 48, "event_id": 3250, "match_id": 2316430}
{"event_timestamp": "2026-05-11 19:54:00", "date": "2017-10-29", "team_1": "pro100", "team_2": "Spirit", "map": "Cobblestone", "result_1": 3, "result_2": 16, "map_winner": 2, "rank_1": 69, "rank_2": 48, "event_id": 3250, "match_id": 2316430}
{"event_timestamp": "2026-05-11 19:54:00", "date": "2017-10-29", "team_1": "Grayhound", "team_2": "5POWER", "map": "Overpass", "result_1": 16, "result_2": 5, "map_winner": 1, "rank_1": 54, "rank_2": 108, "event_id": 3240, "match_id": 2316515}
{"event_timestamp": "2026-05-11 19:54:00", "date": "2017-10-29", "team_1": "Grayhound", "team_2": "5POWER", "map": "Cache", "result_1": 7, "result_2": 16, "map_winner": 2, "rank_1": 54, "rank_2": 108, "event_id": 3240, "match_id": 2316515}
{"event_timestamp": "2026-05-11 19:54:00", "date": "2017-10-29", "team_1": "Complexity", "team_2": "Gale Force", "map": "Cobblestone", "result_1": 16, "result_2": 12, "map_winner": 1, "rank_1": 44, "rank_2": 53, "event_id": 2938, "match_id": 2316487}
{"event_timestamp": "2026-05-11 19:54:00", "date": "2017-10-29", "team_1": "TYLOO", "team_2": "Flash", "map": "Inferno", "result_1": 16, "result_2": 6, "map_winner": 1, "rank_1": 87, "rank_2": 49, "event_id": 3249, "match_id": 2316507}
{"event_timestamp": "2026-05-11 19:54:00", "date": "2017-10-29", "team_1": "TYLOO", "team_2": "Flash", "map": "Cache", "result_1": 12, "result_2": 16, "map_winner": 2, "rank_1": 87, "rank_2": 49, "event_id": 3249, "match_id": 2316507}
{"event_timestamp": "2026-05-11 19:54:00", "date": "2017-10-29", "team_1": "TYLOO", "team_2": "Flash", "map": "Cobblestone", "result_1": 16, "result_2": 14, "map_winner": 1, "rank_1": 87, "rank_2": 49, "event_id": 3249, "match_id": 2316507}
{"event_timestamp": "2026-05-11 19:54:00", "date": "2017-10-29", "team_1": "Flash", "team_2": "MVP PK", "map": "Inferno", "result_1": 16, "result_2": 13, "map_winner": 1, "rank_1": 49, "rank_2": 84, "event_id": 3249, "match_id": 2316506}
{"event_timestamp": "2026-05-11 19:54:00", "date": "2017-10-29", "team_1": "Flash", "team_2": "MVP PK", "map": "Cache", "result_1": 16, "result_2": 9, "map_winner": 1, "rank_1": 49, "rank_2": 84, "event_id": 3249, "match_id": 2316506}
{"event_timestamp": "2026-05-11 19:54:00", "date": "2017-10-29", "team_1": "Complexity", "team_2": "Gale Force", "map": "Cache", "result_1": 16, "result_2": 13, "map_winner": 1, "rank_1": 44, "rank_2": 53, "event_id": 2938, "match_id": 2316487}
{"event_timestamp": "2026-05-11 19:54:00", "date": "2017-10-29", "team_1": "Luminosity", "team_2": "Tempo Storm", "map": "Nuke", "result_1": 16, "result_2": 5, "map_winner": 1, "rank_1": 21, "rank_2": 45, "event_id": 2938, "match_id": 2316486}
{"event_timestamp": "2026-05-11 19:54:00", "date": "2017-10-29", "team_1": "Luminosity", "team_2": "Tempo Storm", "map": "Cobblestone", "result_1": 16, "result_2": 3, "map_winner": 1, "rank_1": 21, "rank_2": 45, "event_id": 2938, "match_id": 2316486}
{"event_timestamp": "2026-05-11 19:54:00", "date": "2017-10-29", "team_1": "Ghost", "team_2": "CLG", "map": "Inferno", "result_1": 14, "result_2": 16, "map_winner": 2, "rank_1": 59, "rank_2": 19, "event_id": 3060, "match_id": 2316492}
{"event_timestamp": "2026-05-11 19:54:00", "date": "2017-10-29", "team_1": "CLG", "team_2": "Ghost", "map": "Cobblestone", "result_1": 16, "result_2": 9, "map_winner": 1, "rank_1": 19, "rank_2": 59, "event_id": 3060, "match_id": 2316491}
{"event_timestamp": "2026-05-11 19:54:00", "date": "2017-10-29", "team_1": "Quantum Bellator Fire", "team_2": "Spirit", "map": "Nuke", "result_1": 16, "result_2": 9, "map_winner": 1, "rank_1": 61, "rank_2": 48, "event_id": 3250, "match_id": 2316431}
{"event_timestamp": "2026-05-11 19:54:00", "date": "2017-10-29", "team_1": "Quantum Bellator Fire", "team_2": "Spirit", "map": "Cobblestone", "result_1": 16, "result_2": 12, "map_winner": 1, "rank_1": 61, "rank_2": 48, "event_id": 3250, "match_id": 2316431}
{"event_timestamp": "2026-05-11 19:54:00", "date": "2017-10-29", "team_1": "PRIDE", "team_2": "passions", "map": "Mirage", "result_1": 3, "result_2": 16, "map_winner": 2, "rank_1": 39, "rank_2": 130, "event_id": 3311, "match_id": 2316528}
{"event_timestamp": "2026-05-11 19:54:00", "date": "2017-10-29", "team_1": "Quantum Bellator Fire", "team_2": "Spirit", "map": "Inferno", "result_1": 9, "result_2": 16, "map_winner": 2, "rank_1": 61, "rank_2": 48, "event_id": 3250, "match_id": 2316431}
{"event_timestamp": "2026-05-11 19:54:00", "date": "2017-10-29", "team_1": "SK", "team_2": "Virtus.pro", "map": "Cobblestone", "result_1": 22, "result_2": 18, "map_winner": 1, "rank_1": 3, "rank_2": 13, "event_id": 3133, "match_id": 2316478}
{"event_timestamp": "2026-05-11 19:54:00", "date": "2017-10-29", "team_1": "WASD", "team_2": "VenatoreS", "map": "Train", "result_1": 16, "result_2": 10, "map_winner": 1, "rank_1": 103, "rank_2": 91, "event_id": 3310, "match_id": 2316551}
{"event_timestamp": "2026-05-11 19:54:00", "date": "2017-10-29", "team_1": "Luminosity", "team_2": "Complexity", "map": "Nuke", "result_1": 16, "result_2": 7, "map_winner": 1, "rank_1": 21, "rank_2": 44, "event_id": 2938, "match_id": 2316534}
{"event_timestamp": "2026-05-11 19:54:00", "date": "2017-10-29", "team_1": "Luminosity", "team_2": "Complexity", "map": "Cobblestone", "result_1": 16, "result_2": 12, "map_winner": 1, "rank_1": 21, "rank_2": 44, "event_id": 2938, "match_id": 2316534}
{"event_timestamp": "2026-05-11 19:54:00", "date": "2017-10-29", "team_1": "Immortals", "team_2": "CLG", "map": "Cache", "result_1": 9, "result_2": 16, "map_winner": 2, "rank_1": 51, "rank_2": 19, "event_id": 3060, "match_id": 2316493}
{"event_timestamp": "2026-05-11 19:54:00", "date": "2017-10-29", "team_1": "fnatic", "team_2": "FaZe", "map": "Train", "result_1": 13, "result_2": 16, "map_winner": 2, "rank_1": 12, "rank_2": 1, "event_id": 3059, "match_id": 2316387}
{"event_timestamp": "2026-05-11 19:54:00", "date": "2017-10-29", "team_1": "FaZe", "team_2": "fnatic", "map": "Mirage", "result_1": 14, "result_2": 16, "map_winner": 2, "rank_1": 1, "rank_2": 12, "event_id": 3059, "match_id": 2316386}
{"event_timestamp": "2026-05-11 19:54:00", "date": "2017-10-29", "team_1": "SK", "team_2": "Virtus.pro", "map": "Inferno", "result_1": 16, "result_2": 6, "map_winner": 1, "rank_1": 3, "rank_2": 13, "event_id": 3133, "match_id": 2316478}
{"event_timestamp": "2026-05-11 19:54:00", "date": "2017-10-29", "team_1": "SK", "team_2": "Virtus.pro", "map": "Train", "result_1": 19, "result_2": 16, "map_winner": 1, "rank_1": 3, "rank_2": 13, "event_id": 3133, "match_id": 2316478}
{"event_timestamp": "2026-05-11 19:54:00", "date": "2017-10-29", "team_1": "SK", "team_2": "Virtus.pro", "map": "Cache", "result_1": 12, "result_2": 16, "map_winner": 2, "rank_1": 3, "rank_2": 13, "event_id": 3133, "match_id": 2316478}
{"event_timestamp": "2026-05-11 19:54:00", "date": "2017-10-29", "team_1": "SK", "team_2": "Virtus.pro", "map": "Mirage", "result_1": 10, "result_2": 16, "map_winner": 2, "rank_1": 3, "rank_2": 13, "event_id": 3133, "match_id": 2316478}
{"event_timestamp": "2026-05-11 19:54:00", "date": "2017-10-29", "team_1": "CLG", "team_2": "Misfits", "map": "Train", "result_1": 16, "result_2": 14, "map_winner": 1, "rank_1": 19, "rank_2": 25, "event_id": 2938, "match_id": 2316533}
{"event_timestamp": "2026-05-11 19:54:00", "date": "2017-10-29", "team_1": "AVANGAR", "team_2": "Quantum Bellator Fire", "map": "Inferno", "result_1": 16, "result_2": 14, "map_winner": 1, "rank_1": 36, "rank_2": 61, "event_id": 3250, "match_id": 2316432}
{"event_timestamp": "2026-05-11 19:54:00", "date": "2017-10-29", "team_1": "CLG", "team_2": "Misfits", "map": "Cache", "result_1": 16, "result_2": 13, "map_winner": 1, "rank_1": 19, "rank_2": 25, "event_id": 2938, "match_id": 2316533}
{"event_timestamp": "2026-05-11 19:54:00", "date": "2017-10-29", "team_1": "PRIDE", "team_2": "TEAM5", "map": "Cache", "result_1": 16, "result_2": 6, "map_winner": 1, "rank_1": 39, "rank_2": 77, "event_id": 3311, "match_id": 2316527}
{"event_timestamp": "2026-05-11 19:54:00", "date": "2017-10-29", "team_1": "AVANGAR", "team_2": "Quantum Bellator Fire", "map": "Cache", "result_1": 19, "result_2": 16, "map_winner": 1, "rank_1": 36, "rank_2": 61, "event_id": 3250, "match_id": 2316432}
{"event_timestamp": "2026-05-11 19:54:00", "date": "2017-10-29", "team_1": "AVANGAR", "team_2": "Quantum Bellator Fire", "map": "Mirage", "result_1": 14, "result_2": 16, "map_winner": 2, "rank_1": 36, "rank_2": 61, "event_id": 3250, "match_id": 2316432}
{"event_timestamp": "2026-05-11 19:54:00", "date": "2017-10-29", "team_1": "RESISTANCE", "team_2": "Spirit Academy", "map": "Inferno", "result_1": 19, "result_2": 17, "map_winner": 1, "rank_1": 145, "rank_2": 73, "event_id": 3310, "match_id": 2316548}
{"event_timestamp": "2026-05-11 19:54:00", "date": "2017-10-29", "team_1": "NiP", "team_2": "Envy", "map": "Cache", "result_1": 11, "result_2": 16, "map_winner": 2, "rank_1": 9, "rank_2": 14, "event_id": 3059, "match_id": 2316384}
{"event_timestamp": "2026-05-11 19:54:00", "date": "2017-10-29", "team_1": "Envy", "team_2": "NiP", "map": "Train", "result_1": 8, "result_2": 16, "map_winner": 2, "rank_1": 14, "rank_2": 9, "event_id": 3059, "match_id": 2316385}
{"event_timestamp": "2026-05-11 19:54:00", "date": "2017-10-29", "team_1": "PRIDE", "team_2": "Singularity", "map": "Mirage", "result_1": 22, "result_2": 20, "map_winner": 1, "rank_1": 39, "rank_2": 47, "event_id": 3228, "match_id": 2316529}
{"event_timestamp": "2026-05-11 19:54:00", "date": "2017-10-28", "team_1": "Signature", "team_2": "Fire Dragoon", "map": "Inferno", "result_1": 14, "result_2": 16, "map_winner": 2, "rank_1": 175, "rank_2": 113, "event_id": 3240, "match_id": 2316512}
{"event_timestamp": "2026-05-11 19:54:00", "date": "2017-10-28", "team_1": "Renegades", "team_2": "TYLOO", "map": "Mirage", "result_1": 16, "result_2": 4, "map_winner": 1, "rank_1": 18, "rank_2": 87, "event_id": 3249, "match_id": 2316505}
{"event_timestamp": "2026-05-11 19:54:00", "date": "2017-10-28", "team_1": "5POWER", "team_2": "Signature", "map": "Mirage", "result_1": 16, "result_2": 19, "map_winner": 2, "rank_1": 108, "rank_2": 175, "event_id": 3240, "match_id": 2316514}
{"event_timestamp": "2026-05-11 19:54:00", "date": "2017-10-28", "team_1": "5POWER", "team_2": "Signature", "map": "Inferno", "result_1": 16, "result_2": 9, "map_winner": 1, "rank_1": 108, "rank_2": 175, "event_id": 3240, "match_id": 2316514}
{"event_timestamp": "2026-05-11 19:54:00", "date": "2017-10-28", "team_1": "5POWER", "team_2": "Signature", "map": "Train", "result_1": 16, "result_2": 11, "map_winner": 1, "rank_1": 108, "rank_2": 175, "event_id": 3240, "match_id": 2316514}
{"event_timestamp": "2026-05-11 19:54:00", "date": "2017-10-28", "team_1": "pro100", "team_2": "Quantum Bellator Fire", "map": "Inferno", "result_1": 14, "result_2": 16, "map_winner": 2, "rank_1": 69, "rank_2": 61, "event_id": 3250, "match_id": 2316427}
{"event_timestamp": "2026-05-11 19:54:00", "date": "2017-10-28", "team_1": "pro100", "team_2": "Quantum Bellator Fire", "map": "Nuke", "result_1": 10, "result_2": 16, "map_winner": 2, "rank_1": 69, "rank_2": 61, "event_id": 3250, "match_id": 2316427}
{"event_timestamp": "2026-05-11 19:54:00", "date": "2017-10-28", "team_1": "Grayhound", "team_2": "Mineski", "map": "Cobblestone", "result_1": 16, "result_2": 12, "map_winner": 1, "rank_1": 54, "rank_2": 160, "event_id": 3240, "match_id": 2316513}
{"event_timestamp": "2026-05-11 19:54:00", "date": "2017-10-28", "team_1": "Grayhound", "team_2": "Mineski", "map": "Inferno", "result_1": 16, "result_2": 13, "map_winner": 1, "rank_1": 54, "rank_2": 160, "event_id": 3240, "match_id": 2316513}
{"event_timestamp": "2026-05-11 19:54:00", "date": "2017-10-28", "team_1": "TYLOO", "team_2": "MVP PK", "map": "Cache", "result_1": 16, "result_2": 12, "map_winner": 1, "rank_1": 87, "rank_2": 84, "event_id": 3249, "match_id": 2316504}
{"event_timestamp": "2026-05-11 19:54:00", "date": "2017-10-28", "team_1": "TYLOO", "team_2": "MVP PK", "map": "Train", "result_1": 16, "result_2": 5, "map_winner": 1, "rank_1": 87, "rank_2": 84, "event_id": 3249, "match_id": 2316504}
{"event_timestamp": "2026-05-11 19:54:00", "date": "2017-10-28", "team_1": "CLG", "team_2": "Cloud9", "map": "Cobblestone", "result_1": 8, "result_2": 16, "map_winner": 2, "rank_1": 19, "rank_2": 6, "event_id": 3060, "match_id": 2316489}
{"event_timestamp": "2026-05-11 19:54:00", "date": "2017-10-28", "team_1": "Signature", "team_2": "Fire Dragoon", "map": "Cache", "result_1": 16, "result_2": 14, "map_winner": 1, "rank_1": 175, "rank_2": 113, "event_id": 3240, "match_id": 2316512}
{"event_timestamp": "2026-05-11 19:54:00", "date": "2017-10-28", "team_1": "Signature", "team_2": "Fire Dragoon", "map": "Mirage", "result_1": 16, "result_2": 8, "map_winner": 1, "rank_1": 175, "rank_2": 113, "event_id": 3240, "match_id": 2316512}
{"event_timestamp": "2026-05-11 19:54:00", "date": "2017-10-28", "team_1": "AKARA", "team_2": "5POWER", "map": "Mirage", "result_1": 4, "result_2": 16, "map_winner": 2, "rank_1": 211, "rank_2": 108, "event_id": 3240, "match_id": 2316511}
{"event_timestamp": "2026-05-11 19:54:00", "date": "2017-10-28", "team_1": "Renegades", "team_2": "TYLOO", "map": "Inferno", "result_1": 19, "result_2": 22, "map_winner": 2, "rank_1": 18, "rank_2": 87, "event_id": 3249, "match_id": 2316505}
{"event_timestamp": "2026-05-11 19:54:00", "date": "2017-10-28", "team_1": "AKARA", "team_2": "5POWER", "map": "Inferno", "result_1": 2, "result_2": 16, "map_winner": 2, "rank_1": 211, "rank_2": 108, "event_id": 3240, "match_id": 2316511}
{"event_timestamp": "2026-05-11 19:54:00", "date": "2017-10-28", "team_1": "Grayhound", "team_2": "Athletico", "map": "Overpass", "result_1": 19, "result_2": 17, "map_winner": 1, "rank_1": 54, "rank_2": 107, "event_id": 3240, "match_id": 2316509}
{"event_timestamp": "2026-05-11 19:54:00", "date": "2017-10-28", "team_1": "Grayhound", "team_2": "Athletico", "map": "Mirage", "result_1": 16, "result_2": 8, "map_winner": 1, "rank_1": 54, "rank_2": 107, "event_id": 3240, "match_id": 2316509}
{"event_timestamp": "2026-05-11 19:54:00", "date": "2017-10-28", "team_1": "Renegades", "team_2": "Flash", "map": "Inferno", "result_1": 16, "result_2": 14, "map_winner": 1, "rank_1": 18, "rank_2": 49, "event_id": 3249, "match_id": 2316503}
{"event_timestamp": "2026-05-11 19:54:00", "date": "2017-10-28", "team_1": "Renegades", "team_2": "Flash", "map": "Cache", "result_1": 16, "result_2": 14, "map_winner": 1, "rank_1": 18, "rank_2": 49, "event_id": 3249, "match_id": 2316503}
{"event_timestamp": "2026-05-11 19:54:00", "date": "2017-10-28", "team_1": "Cloud9", "team_2": "CLG", "map": "Inferno", "result_1": 16, "result_2": 14, "map_winner": 1, "rank_1": 6, "rank_2": 19, "event_id": 3060, "match_id": 2316490}
{"event_timestamp": "2026-05-11 19:54:00", "date": "2017-10-28", "team_1": "Renegades", "team_2": "TYLOO", "map": "Cobblestone", "result_1": 16, "result_2": 6, "map_winner": 1, "rank_1": 18, "rank_2": 87, "event_id": 3249, "match_id": 2316505}
{"event_timestamp": "2026-05-11 19:54:00", "date": "2017-10-28", "team_1": "mousesports", "team_2": "NiP", "map": "Mirage", "result_1": 16, "result_2": 8, "map_winner": 1, "rank_1": 11, "rank_2": 9, "event_id": 3059, "match_id": 2316380}
{"event_timestamp": "2026-05-11 19:54:00", "date": "2017-10-28", "team_1": "Movistar Riders", "team_2": "ex-Outlaws", "map": "Overpass", "result_1": 19, "result_2": 16, "map_winner": 1, "rank_1": 182, "rank_2": 38, "event_id": 3204, "match_id": 2316520}
{"event_timestamp": "2026-05-11 19:54:00", "date": "2017-10-28", "team_1": "Quantum Bellator Fire", "team_2": "AVANGAR", "map": "Cache", "result_1": 13, "result_2": 16, "map_winner": 2, "rank_1": 61, "rank_2": 36, "event_id": 3250, "match_id": 2316429}
{"event_timestamp": "2026-05-11 19:54:00", "date": "2017-10-28", "team_1": "Giants", "team_2": "PANTHERS", "map": "Cache", "result_1": 5, "result_2": 16, "map_winner": 2, "rank_1": 98, "rank_2": 142, "event_id": 3204, "match_id": 2316521}
{"event_timestamp": "2026-05-11 19:54:00", "date": "2017-10-28", "team_1": "CLG", "team_2": "Gorilla Core", "map": "Train", "result_1": 16, "result_2": 4, "map_winner": 1, "rank_1": 19, "rank_2": 206, "event_id": 2938, "match_id": 2316484}
{"event_timestamp": "2026-05-11 19:54:00", "date": "2017-10-28", "team_1": "Misfits", "team_2": "Vault", "map": "Inferno", "result_1": 16, "result_2": 8, "map_winner": 1, "rank_1": 25, "rank_2": 225, "event_id": 2938, "match_id": 2316485}
{"event_timestamp": "2026-05-11 19:54:00", "date": "2017-10-28", "team_1": "Misfits", "team_2": "Vault", "map": "Overpass", "result_1": 16, "result_2": 3, "map_winner": 1, "rank_1": 25, "rank_2": 225, "event_id": 2938, "match_id": 2316485}
{"event_timestamp": "2026-05-11 19:54:00", "date": "2017-10-28", "team_1": "Prophecy", "team_2": "exceL", "map": "Inferno", "result_1": 16, "result_2": 8, "map_winner": 1, "rank_1": 149, "rank_2": 140, "event_id": 3201, "match_id": 2316356}
{"event_timestamp": "2026-05-11 19:54:00", "date": "2017-10-28", "team_1": "NiP", "team_2": "mousesports", "map": "Cache", "result_1": 16, "result_2": 13, "map_winner": 1, "rank_1": 9, "rank_2": 11, "event_id": 3059, "match_id": 2316381}
{"event_timestamp": "2026-05-11 19:54:00", "date": "2017-10-28", "team_1": "Epsilon", "team_2": "Reason", "map": "Overpass", "result_1": 18, "result_2": 22, "map_winner": 2, "rank_1": 65, "rank_2": 106, "event_id": 3201, "match_id": 2316359}
{"event_timestamp": "2026-05-11 19:54:00", "date": "2017-10-28", "team_1": "Quantum Bellator Fire", "team_2": "AVANGAR", "map": "Inferno", "result_1": 16, "result_2": 13, "map_winner": 1, "rank_1": 61, "rank_2": 36, "event_id": 3250, "match_id": 2316429}
{"event_timestamp": "2026-05-11 19:54:00", "date": "2017-10-28", "team_1": "Quantum Bellator Fire", "team_2": "AVANGAR", "map": "Mirage", "result_1": 6, "result_2": 16, "map_winner": 2, "rank_1": 61, "rank_2": 36, "event_id": 3250, "match_id": 2316429}