{"event_timestamp": "2026-05-11 19:51:14", "date": "2018-08-23", "team_1": "North", "team_2": "ENCE", "map": "Mirage", "result_1": 8, "result_2": 16, "map_winner": 2, "rank_1": 10, "rank_2": 13, "event_id": 3972, "match_id": 2325919}
{"event_timestamp": "2026-05-11 19:51:14", "date": "2018-08-23", "team_1": "Heroic", "team_2": "Valiance", "map": "Inferno", "result_1": 16, "result_2": 11, "map_winner": 1, "rank_1": 30, "rank_2": 55, "event_id": 3972, "match_id": 2325920}
{"event_timestamp": "2026-05-11 19:51:14", "date": "2018-08-23", "team_1": "Izako Boars", "team_2": "Nexus", "map": "Mirage", "result_1": 16, "result_2": 13, "map_winner": 1, "rank_1": 105, "rank_2": 91, "event_id": 3999, "match_id": 2325961}
{"event_timestamp": "2026-05-11 19:51:14", "date": "2018-08-23", "team_1": "Ange's Big Toe", "team_2": "eUnited", "map": "Mirage", "result_1": 10, "result_2": 16, "map_winner": 2, "rank_1": 169, "rank_2": 32, "event_id": 3974, "match_id": 2325930}
{"event_timestamp": "2026-05-11 19:51:14", "date": "2018-08-23", "team_1": "Swole Patrol", "team_2": "TeamOne", "map": "Inferno", "result_1": 16, "result_2": 6, "map_winner": 1, "rank_1": 46, "rank_2": 38, "event_id": 3974, "match_id": 2325929}
{"event_timestamp": "2026-05-11 19:51:14", "date": "2018-08-23", "team_1": "Swole Patrol", "team_2": "TeamOne", "map": "Overpass", "result_1": 8, "result_2": 16, "map_winner": 2, "rank_1": 46, "rank_2": 38, "event_id": 3974, "match_id": 2325929}
{"event_timestamp": "2026-05-11 19:51:14", "date": "2018-08-23", "team_1": "Swole Patrol", "team_2": "TeamOne", "map": "Train", "result_1": 16, "result_2": 13, "map_winner": 1, "rank_1": 46, "rank_2": 38, "event_id": 3974, "match_id": 2325929}
{"event_timestamp": "2026-05-11 19:51:14", "date": "2018-08-23", "team_1": "AVANGAR", "team_2": "Gambit", "map": "Overpass", "result_1": 16, "result_2": 4, "map_winner": 1, "rank_1": 31, "rank_2": 18, "event_id": 3972, "match_id": 2325918}
{"event_timestamp": "2026-05-11 19:51:14", "date": "2018-08-23", "team_1": "3DMAX", "team_2": "HAVU", "map": "Train", "result_1": 11, "result_2": 16, "map_winner": 2, "rank_1": 33, "rank_2": 62, "event_id": 3960, "match_id": 2325931}
{"event_timestamp": "2026-05-11 19:51:14", "date": "2018-08-23", "team_1": "3DMAX", "team_2": "HAVU", "map": "Dust2", "result_1": 16, "result_2": 12, "map_winner": 1, "rank_1": 33, "rank_2": 62, "event_id": 3960, "match_id": 2325931}
{"event_timestamp": "2026-05-11 19:51:14", "date": "2018-08-23", "team_1": "Cloud9", "team_2": "BlackOut", "map": "Mirage", "result_1": 16, "result_2": 4, "map_winner": 1, "rank_1": 19, "rank_2": 56, "event_id": 3974, "match_id": 2325927}
{"event_timestamp": "2026-05-11 19:51:14", "date": "2018-08-23", "team_1": "Cloud9", "team_2": "BlackOut", "map": "Cache", "result_1": 6, "result_2": 16, "map_winner": 2, "rank_1": 19, "rank_2": 56, "event_id": 3974, "match_id": 2325927}
{"event_timestamp": "2026-05-11 19:51:14", "date": "2018-08-23", "team_1": "Cloud9", "team_2": "BlackOut", "map": "Overpass", "result_1": 19, "result_2": 17, "map_winner": 1, "rank_1": 19, "rank_2": 56, "event_id": 3974, "match_id": 2325927}
{"event_timestamp": "2026-05-11 19:51:14", "date": "2018-08-23", "team_1": "Vision", "team_2": "Bravado", "map": "Nuke", "result_1": 16, "result_2": 6, "map_winner": 1, "rank_1": 75, "rank_2": 74, "event_id": 3974, "match_id": 2325928}
{"event_timestamp": "2026-05-11 19:51:14", "date": "2018-08-23", "team_1": "Vision", "team_2": "Bravado", "map": "Dust2", "result_1": 11, "result_2": 16, "map_winner": 2, "rank_1": 75, "rank_2": 74, "event_id": 3974, "match_id": 2325928}
{"event_timestamp": "2026-05-11 19:51:14", "date": "2018-08-23", "team_1": "Vision", "team_2": "Bravado", "map": "Overpass", "result_1": 16, "result_2": 5, "map_winner": 1, "rank_1": 75, "rank_2": 74, "event_id": 3974, "match_id": 2325928}
{"event_timestamp": "2026-05-11 19:51:14", "date": "2018-08-23", "team_1": "3DMAX", "team_2": "HAVU", "map": "Cache", "result_1": 16, "result_2": 3, "map_winner": 1, "rank_1": 33, "rank_2": 62, "event_id": 3960, "match_id": 2325931}
{"event_timestamp": "2026-05-11 19:51:14", "date": "2018-08-23", "team_1": "Ange's Big Toe", "team_2": "eUnited", "map": "Overpass", "result_1": 7, "result_2": 16, "map_winner": 2, "rank_1": 169, "rank_2": 32, "event_id": 3974, "match_id": 2325930}
{"event_timestamp": "2026-05-11 19:51:14", "date": "2018-08-23", "team_1": "Fragsters", "team_2": "Space Soldiers", "map": "Train", "result_1": 16, "result_2": 2, "map_winner": 1, "rank_1": 27, "rank_2": 22, "event_id": 3972, "match_id": 2325921}
{"event_timestamp": "2026-05-11 19:51:14", "date": "2018-08-23", "team_1": "GoodJob", "team_2": "DreamEaters", "map": "Inferno", "result_1": 16, "result_2": 11, "map_winner": 1, "rank_1": 81, "rank_2": 60, "event_id": 3940, "match_id": 2325938}
{"event_timestamp": "2026-05-11 19:51:14", "date": "2018-08-23", "team_1": "AVANGAR", "team_2": "Gambit", "map": "Cache", "result_1": 16, "result_2": 11, "map_winner": 1, "rank_1": 31, "rank_2": 18, "event_id": 3972, "match_id": 2325918}
{"event_timestamp": "2026-05-11 19:51:14", "date": "2018-08-23", "team_1": "Fragsters", "team_2": "Space Soldiers", "map": "Inferno", "result_1": 12, "result_2": 16, "map_winner": 2, "rank_1": 27, "rank_2": 22, "event_id": 3972, "match_id": 2325921}
{"event_timestamp": "2026-05-11 19:51:14", "date": "2018-08-23", "team_1": "Fragsters", "team_2": "Space Soldiers", "map": "Mirage", "result_1": 2, "result_2": 16, "map_winner": 2, "rank_1": 27, "rank_2": 22, "event_id": 3972, "match_id": 2325921}
{"event_timestamp": "2026-05-11 19:51:14", "date": "2018-08-23", "team_1": "Heroic", "team_2": "Valiance", "map": "Nuke", "result_1": 16, "result_2": 7, "map_winner": 1, "rank_1": 30, "rank_2": 55, "event_id": 3972, "match_id": 2325920}
{"event_timestamp": "2026-05-11 19:51:14", "date": "2018-08-23", "team_1": "Bpro", "team_2": "Sharks", "map": "Inferno", "result_1": 12, "result_2": 16, "map_winner": 2, "rank_1": 64, "rank_2": 66, "event_id": 3960, "match_id": 2325932}
{"event_timestamp": "2026-05-11 19:51:14", "date": "2018-08-23", "team_1": "Bpro", "team_2": "Sharks", "map": "Cache", "result_1": 16, "result_2": 11, "map_winner": 1, "rank_1": 64, "rank_2": 66, "event_id": 3960, "match_id": 2325932}
{"event_timestamp": "2026-05-11 19:51:14", "date": "2018-08-23", "team_1": "Bpro", "team_2": "Sharks", "map": "Nuke", "result_1": 7, "result_2": 16, "map_winner": 2, "rank_1": 64, "rank_2": 66, "event_id": 3960, "match_id": 2325932}
{"event_timestamp": "2026-05-11 19:51:14", "date": "2018-08-23", "team_1": "GoodJob", "team_2": "DreamEaters", "map": "Cache", "result_1": 8, "result_2": 16, "map_winner": 2, "rank_1": 81, "rank_2": 60, "event_id": 3940, "match_id": 2325938}
{"event_timestamp": "2026-05-11 19:51:14", "date": "2018-08-23", "team_1": "GoodJob", "team_2": "DreamEaters", "map": "Mirage", "result_1": 6, "result_2": 16, "map_winner": 2, "rank_1": 81, "rank_2": 60, "event_id": 3940, "match_id": 2325938}
{"event_timestamp": "2026-05-11 19:51:14", "date": "2018-08-22", "team_1": "Yeah", "team_2": "DETONA", "map": "Train", "result_1": 7, "result_2": 16, "map_winner": 2, "rank_1": 198, "rank_2": 200, "event_id": 3967, "match_id": 2325616}
{"event_timestamp": "2026-05-11 19:51:14", "date": "2018-08-22", "team_1": "Taboo", "team_2": "Grayhound", "map": "Inferno", "result_1": 8, "result_2": 16, "map_winner": 2, "rank_1": 218, "rank_2": 40, "event_id": 3882, "match_id": 2325890}
{"event_timestamp": "2026-05-11 19:51:14", "date": "2018-08-22", "team_1": "Grayhound", "team_2": "Taboo", "map": "Cache", "result_1": 16, "result_2": 6, "map_winner": 1, "rank_1": 40, "rank_2": 218, "event_id": 3882, "match_id": 2325889}
{"event_timestamp": "2026-05-11 19:51:14", "date": "2018-08-22", "team_1": "SYF", "team_2": "Ground Zero", "map": "Dust2", "result_1": 12, "result_2": 16, "map_winner": 2, "rank_1": 172, "rank_2": 165, "event_id": 3882, "match_id": 2325888}
{"event_timestamp": "2026-05-11 19:51:14", "date": "2018-08-22", "team_1": "Chiefs", "team_2": "Dynasty", "map": "Cache", "result_1": 16, "result_2": 11, "map_winner": 1, "rank_1": 63, "rank_2": 205, "event_id": 3882, "match_id": 2325884}
{"event_timestamp": "2026-05-11 19:51:14", "date": "2018-08-22", "team_1": "Dynasty", "team_2": "Chiefs", "map": "Inferno", "result_1": 14, "result_2": 16, "map_winner": 2, "rank_1": 205, "rank_2": 63, "event_id": 3882, "match_id": 2325883}
{"event_timestamp": "2026-05-11 19:51:14", "date": "2018-08-22", "team_1": "Ground Zero", "team_2": "SYF", "map": "Mirage", "result_1": 16, "result_2": 10, "map_winner": 1, "rank_1": 165, "rank_2": 172, "event_id": 3882, "match_id": 2325887}
{"event_timestamp": "2026-05-11 19:51:14", "date": "2018-08-22", "team_1": "Ange's Big Toe", "team_2": "iNTACT", "map": "Mirage", "result_1": 16, "result_2": 10, "map_winner": 1, "rank_1": 169, "rank_2": 95, "event_id": 3973, "match_id": 2325876}
{"event_timestamp": "2026-05-11 19:51:14", "date": "2018-08-22", "team_1": "Ange's Big Toe", "team_2": "iNTACT", "map": "Overpass", "result_1": 16, "result_2": 14, "map_winner": 1, "rank_1": 169, "rank_2": 95, "event_id": 3973, "match_id": 2325876}
{"event_timestamp": "2026-05-11 19:51:14", "date": "2018-08-22", "team_1": "BlackOut", "team_2": "RESOLUTE", "map": "Mirage", "result_1": 16, "result_2": 9, "map_winner": 1, "rank_1": 56, "rank_2": 97, "event_id": 3973, "match_id": 2325878}
{"event_timestamp": "2026-05-11 19:51:14", "date": "2018-08-22", "team_1": "C4", "team_2": "PITS", "map": "Cache", "result_1": 14, "result_2": 16, "map_winner": 2, "rank_1": 163, "rank_2": 204, "event_id": 3955, "match_id": 2325860}
{"event_timestamp": "2026-05-11 19:51:14", "date": "2018-08-22", "team_1": "C4", "team_2": "PITS", "map": "Mirage", "result_1": 11, "result_2": 16, "map_winner": 2, "rank_1": 163, "rank_2": 204, "event_id": 3955, "match_id": 2325860}
{"event_timestamp": "2026-05-11 19:51:14", "date": "2018-08-22", "team_1": "TeamOne", "team_2": "Grizzlys", "map": "Inferno", "result_1": 16, "result_2": 3, "map_winner": 1, "rank_1": 38, "rank_2": 107, "event_id": 3973, "match_id": 2325877}
{"event_timestamp": "2026-05-11 19:51:14", "date": "2018-08-22", "team_1": "TeamOne", "team_2": "Grizzlys", "map": "Cache", "result_1": 16, "result_2": 2, "map_winner": 1, "rank_1": 38, "rank_2": 107, "event_id": 3973, "match_id": 2325877}
{"event_timestamp": "2026-05-11 19:51:14", "date": "2018-08-22", "team_1": "BlackOut", "team_2": "RESOLUTE", "map": "Overpass", "result_1": 9, "result_2": 16, "map_winner": 2, "rank_1": 56, "rank_2": 97, "event_id": 3973, "match_id": 2325878}
{"event_timestamp": "2026-05-11 19:51:14", "date": "2018-08-22", "team_1": "3DMAX", "team_2": "Nordavind", "map": "Dust2", "result_1": 16, "result_2": 14, "map_winner": 1, "rank_1": 33, "rank_2": 69, "event_id": 3960, "match_id": 2325902}
{"event_timestamp": "2026-05-11 19:51:14", "date": "2018-08-22", "team_1": "BlackOut", "team_2": "RESOLUTE", "map": "Inferno", "result_1": 16, "result_2": 13, "map_winner": 1, "rank_1": 56, "rank_2": 97, "event_id": 3973, "match_id": 2325878}
{"event_timestamp": "2026-05-11 19:51:14", "date": "2018-08-22", "team_1": "Wild", "team_2": "Furious", "map": "Train", "result_1": 16, "result_2": 7, "map_winner": 1, "rank_1": 127, "rank_2": 189, "event_id": 3967, "match_id": 2325613}
{"event_timestamp": "2026-05-11 19:51:14", "date": "2018-08-22", "team_1": "C4", "team_2": "Isurus", "map": "Inferno", "result_1": 14, "result_2": 16, "map_winner": 2, "rank_1": 163, "rank_2": 174, "event_id": 3967, "match_id": 2325614}
{"event_timestamp": "2026-05-11 19:51:14", "date": "2018-08-22", "team_1": "GoodJob", "team_2": "FriendlyFire", "map": "Inferno", "result_1": 16, "result_2": 6, "map_winner": 1, "rank_1": 81, "rank_2": 73, "event_id": 3977, "match_id": 2325784}
{"event_timestamp": "2026-05-11 19:51:14", "date": "2018-08-22", "team_1": "DreamEaters", "team_2": "WINside", "map": "Mirage", "result_1": 16, "result_2": 8, "map_winner": 1, "rank_1": 60, "rank_2": 131, "event_id": 3940, "match_id": 2325900}
{"event_timestamp": "2026-05-11 19:51:14", "date": "2018-08-22", "team_1": "3DMAX", "team_2": "Nordavind", "map": "Overpass", "result_1": 10, "result_2": 16, "map_winner": 2, "rank_1": 33, "rank_2": 69, "event_id": 3960, "match_id": 2325902}
{"event_timestamp": "2026-05-11 19:51:14", "date": "2018-08-22", "team_1": "DreamEaters", "team_2": "WINside", "map": "Train", "result_1": 16, "result_2": 8, "map_winner": 1, "rank_1": 60, "rank_2": 131, "event_id": 3940, "match_id": 2325900}
{"event_timestamp": "2026-05-11 19:51:14", "date": "2018-08-22", "team_1": "FURIA", "team_2": "Swole Patrol", "map": "Mirage", "result_1": 16, "result_2": 5, "map_winner": 1, "rank_1": 53, "rank_2": 46, "event_id": 3995, "match_id": 2325933}
{"event_timestamp": "2026-05-11 19:51:14", "date": "2018-08-22", "team_1": "FURIA", "team_2": "Swole Patrol", "map": "Overpass", "result_1": 5, "result_2": 16, "map_winner": 2, "rank_1": 53, "rank_2": 46, "event_id": 3995, "match_id": 2325933}
{"event_timestamp": "2026-05-11 19:51:14", "date": "2018-08-22", "team_1": "FURIA", "team_2": "Swole Patrol", "map": "Train", "result_1": 16, "result_2": 11, "map_winner": 1, "rank_1": 53, "rank_2": 46, "event_id": 3995, "match_id": 2325933}
{"event_timestamp": "2026-05-11 19:51:14", "date": "2018-08-22", "team_1": "Swole Patrol", "team_2": "Infamous", "map": "Train", "result_1": 16, "result_2": 6, "map_winner": 1, "rank_1": 46, "rank_2": 123, "event_id": 3995, "match_id": 2325908}
{"event_timestamp": "2026-05-11 19:51:14", "date": "2018-08-22", "team_1": "Swole Patrol", "team_2": "Infamous", "map": "Inferno", "result_1": 13, "result_2": 16, "map_winner": 2, "rank_1": 46, "rank_2": 123, "event_id": 3995, "match_id": 2325908}
{"event_timestamp": "2026-05-11 19:51:14", "date": "2018-08-22", "team_1": "Swole Patrol", "team_2": "Infamous", "map": "Cache", "result_1": 16, "result_2": 14, "map_winner": 1, "rank_1": 46, "rank_2": 123, "event_id": 3995, "match_id": 2325908}
{"event_timestamp": "2026-05-11 19:51:14", "date": "2018-08-22", "team_1": "3DMAX", "team_2": "Nordavind", "map": "Inferno", "result_1": 16, "result_2": 12, "map_winner": 1, "rank_1": 33, "rank_2": 69, "event_id": 3960, "match_id": 2325902}
{"event_timestamp": "2026-05-11 19:51:14", "date": "2018-08-22", "team_1": "Sharks", "team_2": "Nordavind", "map": "Mirage", "result_1": 16, "result_2": 14, "map_winner": 1, "rank_1": 66, "rank_2": 69, "event_id": 3960, "match_id": 2325904}
{"event_timestamp": "2026-05-11 19:51:14", "date": "2018-08-22", "team_1": "HAVU", "team_2": "WASD", "map": "Nuke", "result_1": 14, "result_2": 16, "map_winner": 2, "rank_1": 62, "rank_2": 193, "event_id": 3946, "match_id": 2325507}
{"event_timestamp": "2026-05-11 19:51:14", "date": "2018-08-22", "team_1": "HAVU", "team_2": "WASD", "map": "Train", "result_1": 16, "result_2": 13, "map_winner": 1, "rank_1": 62, "rank_2": 193, "event_id": 3946, "match_id": 2325507}
{"event_timestamp": "2026-05-11 19:51:14", "date": "2018-08-22", "team_1": "HAVU", "team_2": "WASD", "map": "Mirage", "result_1": 16, "result_2": 10, "map_winner": 1, "rank_1": 62, "rank_2": 193, "event_id": 3946, "match_id": 2325507}
{"event_timestamp": "2026-05-11 19:51:14", "date": "2018-08-22", "team_1": "HAVU", "team_2": "x-kom", "map": "Mirage", "result_1": 16, "result_2": 11, "map_winner": 1, "rank_1": 62, "rank_2": 87, "event_id": 3960, "match_id": 2325903}
{"event_timestamp": "2026-05-11 19:51:14", "date": "2018-08-22", "team_1": "HAVU", "team_2": "x-kom", "map": "Dust2", "result_1": 16, "result_2": 13, "map_winner": 1, "rank_1": 62, "rank_2": 87, "event_id": 3960, "match_id": 2325903}
{"event_timestamp": "2026-05-11 19:51:14", "date": "2018-08-22", "team_1": "Sharks", "team_2": "Nordavind", "map": "Nuke", "result_1": 16, "result_2": 11, "map_winner": 1, "rank_1": 66, "rank_2": 69, "event_id": 3960, "match_id": 2325904}
{"event_timestamp": "2026-05-11 19:51:14", "date": "2018-08-21", "team_1": "Atlants", "team_2": "Chaos", "map": "Dust2", "result_1": 9, "result_2": 16, "map_winner": 2, "rank_1": 336, "rank_2": 88, "event_id": 3971, "match_id": 2325855}
{"event_timestamp": "2026-05-11 19:51:14", "date": "2018-08-21", "team_1": "WINside", "team_2": "Unique", "map": "Train", "result_1": 16, "result_2": 19, "map_winner": 2, "rank_1": 131, "rank_2": 89, "event_id": 3940, "match_id": 2325792}
{"event_timestamp": "2026-05-11 19:51:14", "date": "2018-08-21", "team_1": "Taboo", "team_2": "MC", "map": "Inferno", "result_1": 19, "result_2": 22, "map_winner": 2, "rank_1": 218, "rank_2": 332, "event_id": 3978, "match_id": 2325879}
{"event_timestamp": "2026-05-11 19:51:14", "date": "2018-08-21", "team_1": "Taboo", "team_2": "MC", "map": "Nuke", "result_1": 12, "result_2": 16, "map_winner": 2, "rank_1": 218, "rank_2": 332, "event_id": 3978, "match_id": 2325879}
{"event_timestamp": "2026-05-11 19:51:14", "date": "2018-08-21", "team_1": "WINside", "team_2": "Unique", "map": "Dust2", "result_1": 16, "result_2": 13, "map_winner": 1, "rank_1": 131, "rank_2": 89, "event_id": 3940, "match_id": 2325792}
{"event_timestamp": "2026-05-11 19:51:14", "date": "2018-08-21", "team_1": "Tricked", "team_2": "HAVU", "map": "Cache", "result_1": 16, "result_2": 14, "map_winner": 1, "rank_1": 76, "rank_2": 62, "event_id": 3960, "match_id": 2325843}
{"event_timestamp": "2026-05-11 19:51:14", "date": "2018-08-21", "team_1": "WINside", "team_2": "Unique", "map": "Mirage", "result_1": 16, "result_2": 14, "map_winner": 1, "rank_1": 131, "rank_2": 89, "event_id": 3940, "match_id": 2325792}
{"event_timestamp": "2026-05-11 19:51:14", "date": "2018-08-21", "team_1": "Tricked", "team_2": "HAVU", "map": "Nuke", "result_1": 6, "result_2": 16, "map_winner": 2, "rank_1": 76, "rank_2": 62, "event_id": 3960, "match_id": 2325843}
{"event_timestamp": "2026-05-11 19:51:14", "date": "2018-08-21", "team_1": "MVP PK", "team_2": "SCARZ Absolute", "map": "Inferno", "result_1": 16, "result_2": 5, "map_winner": 1, "rank_1": 52, "rank_2": 59, "event_id": 3970, "match_id": 2325839}
{"event_timestamp": "2026-05-11 19:51:14", "date": "2018-08-21", "team_1": "Tricked", "team_2": "HAVU", "map": "Dust2", "result_1": 9, "result_2": 16, "map_winner": 2, "rank_1": 76, "rank_2": 62, "event_id": 3960, "match_id": 2325843}
{"event_timestamp": "2026-05-11 19:51:14", "date": "2018-08-21", "team_1": "MVP PK", "team_2": "SCARZ Absolute", "map": "Cache", "result_1": 16, "result_2": 9, "map_winner": 1, "rank_1": 52, "rank_2": 59, "event_id": 3970, "match_id": 2325839}
{"event_timestamp": "2026-05-11 19:51:14", "date": "2018-08-21", "team_1": "Yeah", "team_2": "Isurus", "map": "Dust2", "result_1": 16, "result_2": 14, "map_winner": 1, "rank_1": 198, "rank_2": 174, "event_id": 3967, "match_id": 2325612}
{"event_timestamp": "2026-05-11 19:51:14", "date": "2018-08-21", "team_1": "SCARZ Absolute", "team_2": "BOOT-d[S]", "map": "Inferno", "result_1": 9, "result_2": 16, "map_winner": 2, "rank_1": 59, "rank_2": 42, "event_id": 3970, "match_id": 2325838}
{"event_timestamp": "2026-05-11 19:51:14", "date": "2018-08-21", "team_1": "SCARZ Absolute", "team_2": "BOOT-d[S]", "map": "Cache", "result_1": 16, "result_2": 14, "map_winner": 1, "rank_1": 59, "rank_2": 42, "event_id": 3970, "match_id": 2325838}
{"event_timestamp": "2026-05-11 19:51:14", "date": "2018-08-21", "team_1": "SCARZ Absolute", "team_2": "BOOT-d[S]", "map": "Mirage", "result_1": 16, "result_2": 10, "map_winner": 1, "rank_1": 59, "rank_2": 42, "event_id": 3970, "match_id": 2325838}
{"event_timestamp": "2026-05-11 19:51:14", "date": "2018-08-21", "team_1": "Velocity", "team_2": "Fam143", "map": "Nuke", "result_1": 16, "result_2": 11, "map_winner": 1, "rank_1": 99, "rank_2": 102, "event_id": 3973, "match_id": 2325862}
{"event_timestamp": "2026-05-11 19:51:14", "date": "2018-08-21", "team_1": "DETONA", "team_2": "C4", "map": "Inferno", "result_1": 16, "result_2": 14, "map_winner": 1, "rank_1": 200, "rank_2": 163, "event_id": 3967, "match_id": 2325610}
{"event_timestamp": "2026-05-11 19:51:14", "date": "2018-08-21", "team_1": "BlackOut", "team_2": "Uber To Your Crib", "map": "Inferno", "result_1": 16, "result_2": 11, "map_winner": 1, "rank_1": 56, "rank_2": 160, "event_id": 3973, "match_id": 2325863}
{"event_timestamp": "2026-05-11 19:51:14", "date": "2018-08-21", "team_1": "Valiance", "team_2": "Chaos", "map": "Dust2", "result_1": 16, "result_2": 4, "map_winner": 1, "rank_1": 55, "rank_2": 88, "event_id": 3971, "match_id": 2325858}
{"event_timestamp": "2026-05-11 19:51:14", "date": "2018-08-21", "team_1": "Wild", "team_2": "FURIA Inagame", "map": "Inferno", "result_1": 22, "result_2": 19, "map_winner": 1, "rank_1": 127, "rank_2": 199, "event_id": 3967, "match_id": 2325609}
{"event_timestamp": "2026-05-11 19:51:14", "date": "2018-08-21", "team_1": "3DMAX", "team_2": "AVANGAR", "map": "Overpass", "result_1": 7, "result_2": 16, "map_winner": 2, "rank_1": 33, "rank_2": 31, "event_id": 3971, "match_id": 2325854}
{"event_timestamp": "2026-05-11 19:51:14", "date": "2018-08-21", "team_1": "Valiance", "team_2": "Chaos", "map": "Inferno", "result_1": 16, "result_2": 12, "map_winner": 1, "rank_1": 55, "rank_2": 88, "event_id": 3971, "match_id": 2325858}
{"event_timestamp": "2026-05-11 19:51:14", "date": "2018-08-21", "team_1": "DreamEaters", "team_2": "HAVU", "map": "Train", "result_1": 2, "result_2": 16, "map_winner": 2, "rank_1": 60, "rank_2": 62, "event_id": 3977, "match_id": 2325782}
{"event_timestamp": "2026-05-11 19:51:14", "date": "2018-08-21", "team_1": "Bulldozer", "team_2": "Uranus", "map": "Inferno", "result_1": 16, "result_2": 3, "map_winner": 1, "rank_1": 259, "rank_2": 242, "event_id": 3955, "match_id": 2325861}
{"event_timestamp": "2026-05-11 19:51:14", "date": "2018-08-21", "team_1": "FURIA", "team_2": "Hysteria", "map": "Mirage", "result_1": 16, "result_2": 7, "map_winner": 1, "rank_1": 53, "rank_2": 93, "event_id": 3995, "match_id": 2325905}
{"event_timestamp": "2026-05-11 19:51:14", "date": "2018-08-21", "team_1": "Fragsters", "team_2": "AVANGAR", "map": "Dust2", "result_1": 10, "result_2": 16, "map_winner": 2, "rank_1": 27, "rank_2": 31, "event_id": 3971, "match_id": 2325859}
{"event_timestamp": "2026-05-11 19:51:14", "date": "2018-08-21", "team_1": "Bulldozer", "team_2": "Uranus", "map": "Overpass", "result_1": 16, "result_2": 8, "map_winner": 1, "rank_1": 259, "rank_2": 242, "event_id": 3955, "match_id": 2325861}
{"event_timestamp": "2026-05-11 19:51:14", "date": "2018-08-21", "team_1": "Chaos", "team_2": "Fragsters", "map": "Dust2", "result_1": 16, "result_2": 19, "map_winner": 2, "rank_1": 88, "rank_2": 27, "event_id": 3971, "match_id": 2325899}
{"event_timestamp": "2026-05-11 19:51:14", "date": "2018-08-21", "team_1": "Chaos", "team_2": "Fragsters", "map": "Train", "result_1": 16, "result_2": 19, "map_winner": 2, "rank_1": 88, "rank_2": 27, "event_id": 3971, "match_id": 2325899}
{"event_timestamp": "2026-05-11 19:51:14", "date": "2018-08-21", "team_1": "W7M", "team_2": "INTZ", "map": "Cache", "result_1": 16, "result_2": 11, "map_winner": 1, "rank_1": 178, "rank_2": 188, "event_id": 3814, "match_id": 2325499}
{"event_timestamp": "2026-05-11 19:51:14", "date": "2018-08-21", "team_1": "CLG Red", "team_2": "Infamous", "map": "Inferno", "result_1": 7, "result_2": 16, "map_winner": 2, "rank_1": 128, "rank_2": 123, "event_id": 3995, "match_id": 2325907}
{"event_timestamp": "2026-05-11 19:51:14", "date": "2018-08-21", "team_1": "Swole Patrol", "team_2": "Excelerate", "map": "Inferno", "result_1": 16, "result_2": 6, "map_winner": 1, "rank_1": 46, "rank_2": 103, "event_id": 3995, "match_id": 2325906}
{"event_timestamp": "2026-05-11 19:51:14", "date": "2018-08-21", "team_1": "W7M", "team_2": "INTZ", "map": "Train", "result_1": 16, "result_2": 3, "map_winner": 1, "rank_1": 178, "rank_2": 188, "event_id": 3814, "match_id": 2325499}
{"event_timestamp": "2026-05-11 19:51:14", "date": "2018-08-21", "team_1": "x-kom", "team_2": "Bpro", "map": "Overpass", "result_1": 7, "result_2": 16, "map_winner": 2, "rank_1": 87, "rank_2": 64, "event_id": 3960, "match_id": 2325844}
{"event_timestamp": "2026-05-11 19:51:14", "date": "2018-08-21", "team_1": "x-kom", "team_2": "Bpro", "map": "Inferno", "result_1": 5, "result_2": 16, "map_winner": 2, "rank_1": 87, "rank_2": 64, "event_id": 3960, "match_id": 2325844}
{"event_timestamp": "2026-05-11 19:51:14", "date": "2018-08-21", "team_1": "Endpoint", "team_2": "Squared", "map": "Overpass", "result_1": 12, "result_2": 16, "map_winner": 2, "rank_1": 84, "rank_2": 194, "event_id": 3946, "match_id": 2325649}
{"event_timestamp": "2026-05-11 19:51:14", "date": "2018-08-21", "team_1": "Endpoint", "team_2": "Squared", "map": "Mirage", "result_1": 16, "result_2": 9, "map_winner": 1, "rank_1": 84, "rank_2": 194, "event_id": 3946, "match_id": 2325649}
{"event_timestamp": "2026-05-11 19:51:14", "date": "2018-08-21", "team_1": "Endpoint", "team_2": "Squared", "map": "Train", "result_1": 19, "result_2": 15, "map_winner": 1, "rank_1": 84, "rank_2": 194, "event_id": 3946, "match_id": 2325649}
{"event_timestamp": "2026-05-11 19:51:14", "date": "2018-08-21", "team_1": "Fragsters", "team_2": "AVANGAR", "map": "Mirage", "result_1": 12, "result_2": 16, "map_winner": 2, "rank_1": 27, "rank_2": 31, "event_id": 3971, "match_id": 2325859}
{"event_timestamp": "2026-05-11 19:51:14", "date": "2018-08-21", "team_1": "Fragsters", "team_2": "AVANGAR", "map": "Inferno", "result_1": 16, "result_2": 7, "map_winner": 1, "rank_1": 27, "rank_2": 31, "event_id": 3971, "match_id": 2325859}
{"event_timestamp": "2026-05-11 19:51:14", "date": "2018-08-20", "team_1": "AGO", "team_2": "3DMAX", "map": "Dust2", "result_1": 16, "result_2": 9, "map_winner": 1, "rank_1": 29, "rank_2": 36, "event_id": 3992, "match_id": 2325829}
{"event_timestamp": "2026-05-11 19:51:14", "date": "2018-08-20", "team_1": "MVP PK", "team_2": "CyberZen", "map": "Nuke", "result_1": 16, "result_2": 19, "map_winner": 2, "rank_1": 73, "rank_2": 97, "event_id": 3937, "match_id": 2325735}
{"event_timestamp": "2026-05-11 19:51:14", "date": "2018-08-20", "team_1": "MVP PK", "team_2": "CyberZen", "map": "Mirage", "result_1": 13, "result_2": 16, "map_winner": 2, "rank_1": 73, "rank_2": 97, "event_id": 3937, "match_id": 2325735}
{"event_timestamp": "2026-05-11 19:51:14", "date": "2018-08-20", "team_1": "Royal Bandits", "team_2": "Smoke Criminals", "map": "Nuke", "result_1": 9, "result_2": 16, "map_winner": 2, "rank_1": 119, "rank_2": 83, "event_id": 3992, "match_id": 2325830}
{"event_timestamp": "2026-05-11 19:51:14", "date": "2018-08-20", "team_1": "Royal Bandits", "team_2": "Smoke Criminals", "map": "Cache", "result_1": 16, "result_2": 8, "map_winner": 1, "rank_1": 119, "rank_2": 83, "event_id": 3992, "match_id": 2325830}
{"event_timestamp": "2026-05-11 19:51:14", "date": "2018-08-20", "team_1": "Royal Bandits", "team_2": "Smoke Criminals", "map": "Inferno", "result_1": 10, "result_2": 16, "map_winner": 2, "rank_1": 119, "rank_2": 83, "event_id": 3992, "match_id": 2325830}
{"event_timestamp": "2026-05-11 19:51:14", "date": "2018-08-20", "team_1": "AGO", "team_2": "3DMAX", "map": "Cache", "result_1": 16, "result_2": 5, "map_winner": 1, "rank_1": 29, "rank_2": 36, "event_id": 3992, "match_id": 2325829}
{"event_timestamp": "2026-05-11 19:51:14", "date": "2018-08-20", "team_1": "AGO", "team_2": "3DMAX", "map": "Inferno", "result_1": 11, "result_2": 16, "map_winner": 2, "rank_1": 29, "rank_2": 36, "event_id": 3992, "match_id": 2325829}
{"event_timestamp": "2026-05-11 19:51:14", "date": "2018-08-20", "team_1": "AGO", "team_2": "Smoke Criminals", "map": "Cache", "result_1": 16, "result_2": 13, "map_winner": 1, "rank_1": 29, "rank_2": 83, "event_id": 3992, "match_id": 2325831}
{"event_timestamp": "2026-05-11 19:51:14", "date": "2018-08-20", "team_1": "CyberZen", "team_2": "BOOT-d[S]", "map": "Train", "result_1": 9, "result_2": 16, "map_winner": 2, "rank_1": 97, "rank_2": 40, "event_id": 3937, "match_id": 2325734}
{"event_timestamp": "2026-05-11 19:51:14", "date": "2018-08-20", "team_1": "CyberZen", "team_2": "BOOT-d[S]", "map": "Inferno", "result_1": 16, "result_2": 5, "map_winner": 1, "rank_1": 97, "rank_2": 40, "event_id": 3937, "match_id": 2325734}
{"event_timestamp": "2026-05-11 19:51:14", "date": "2018-08-20", "team_1": "Avalanche", "team_2": "Wild", "map": "Mirage", "result_1": 14, "result_2": 16, "map_winner": 2, "rank_1": 253, "rank_2": 136, "event_id": 3771, "match_id": 2325804}
{"event_timestamp": "2026-05-11 19:51:14", "date": "2018-08-20", "team_1": "Avalanche", "team_2": "Wild", "map": "Nuke", "result_1": 10, "result_2": 16, "map_winner": 2, "rank_1": 253, "rank_2": 136, "event_id": 3771, "match_id": 2325804}
{"event_timestamp": "2026-05-11 19:51:14", "date": "2018-08-20", "team_1": "CyberZen", "team_2": "BOOT-d[S]", "map": "Nuke", "result_1": 16, "result_2": 14, "map_winner": 1, "rank_1": 97, "rank_2": 40, "event_id": 3937, "match_id": 2325734}
{"event_timestamp": "2026-05-11 19:51:14", "date": "2018-08-20", "team_1": "BOOT-d[S]", "team_2": "EHOME", "map": "Inferno", "result_1": 16, "result_2": 14, "map_winner": 1, "rank_1": 40, "rank_2": 123, "event_id": 3937, "match_id": 2325732}
{"event_timestamp": "2026-05-11 19:51:14", "date": "2018-08-20", "team_1": "BOOT-d[S]", "team_2": "EHOME", "map": "Train", "result_1": 16, "result_2": 10, "map_winner": 1, "rank_1": 40, "rank_2": 123, "event_id": 3937, "match_id": 2325732}
{"event_timestamp": "2026-05-11 19:51:14", "date": "2018-08-20", "team_1": "C4", "team_2": "Uranus", "map": "Mirage", "result_1": 16, "result_2": 1, "map_winner": 1, "rank_1": 172, "rank_2": 242, "event_id": 3955, "match_id": 2325607}
{"event_timestamp": "2026-05-11 19:51:14", "date": "2018-08-20", "team_1": "MVP PK", "team_2": "CyberZen", "map": "Inferno", "result_1": 16, "result_2": 14, "map_winner": 1, "rank_1": 73, "rank_2": 97, "event_id": 3937, "match_id": 2325735}
{"event_timestamp": "2026-05-11 19:51:14", "date": "2018-08-20", "team_1": "C4", "team_2": "Uranus", "map": "Inferno", "result_1": 16, "result_2": 12, "map_winner": 1, "rank_1": 172, "rank_2": 242, "event_id": 3955, "match_id": 2325607}
{"event_timestamp": "2026-05-11 19:51:14", "date": "2018-08-20", "team_1": "AGO", "team_2": "Smoke Criminals", "map": "Overpass", "result_1": 16, "result_2": 2, "map_winner": 1, "rank_1": 29, "rank_2": 83, "event_id": 3992, "match_id": 2325831}
{"event_timestamp": "2026-05-11 19:51:14", "date": "2018-08-20", "team_1": "AVANGAR", "team_2": "Quantum Bellator Fire", "map": "Mirage", "result_1": 16, "result_2": 11, "map_winner": 1, "rank_1": 31, "rank_2": 116, "event_id": 3971, "match_id": 2325853}
{"event_timestamp": "2026-05-11 19:51:14", "date": "2018-08-20", "team_1": "Chaos", "team_2": "SJ", "map": "Inferno", "result_1": 12, "result_2": 16, "map_winner": 2, "rank_1": 76, "rank_2": 68, "event_id": 3977, "match_id": 2325781}
{"event_timestamp": "2026-05-11 19:51:14", "date": "2018-08-20", "team_1": "Surge", "team_2": "Ground Zero", "map": "Dust2", "result_1": 3, "result_2": 16, "map_winner": 2, "rank_1": 162, "rank_2": 160, "event_id": 3989, "match_id": 2325997}
{"event_timestamp": "2026-05-11 19:51:14", "date": "2018-08-20", "team_1": "PITS", "team_2": "Bulldozer", "map": "Cache", "result_1": 16, "result_2": 8, "map_winner": 1, "rank_1": 204, "rank_2": 259, "event_id": 3955, "match_id": 2325608}
{"event_timestamp": "2026-05-11 19:51:14", "date": "2018-08-20", "team_1": "PITS", "team_2": "Bulldozer", "map": "Dust2", "result_1": 16, "result_2": 3, "map_winner": 1, "rank_1": 204, "rank_2": 259, "event_id": 3955, "match_id": 2325608}
{"event_timestamp": "2026-05-11 19:51:14", "date": "2018-08-20", "team_1": "Fragsters", "team_2": "LDLC", "map": "Inferno", "result_1": 16, "result_2": 9, "map_winner": 1, "rank_1": 27, "rank_2": 54, "event_id": 3971, "match_id": 2325857}
{"event_timestamp": "2026-05-11 19:51:14", "date": "2018-08-20", "team_1": "Valiance", "team_2": "Imperial", "map": "Mirage", "result_1": 16, "result_2": 8, "map_winner": 1, "rank_1": 55, "rank_2": 25, "event_id": 3971, "match_id": 2325856}
{"event_timestamp": "2026-05-11 19:51:14", "date": "2018-08-20", "team_1": "PITS", "team_2": "Bulldozer", "map": "Inferno", "result_1": 14, "result_2": 16, "map_winner": 2, "rank_1": 204, "rank_2": 259, "event_id": 3955, "match_id": 2325608}
{"event_timestamp": "2026-05-11 19:51:14", "date": "2018-08-20", "team_1": "SJ", "team_2": "Chaos", "map": "Cache", "result_1": 14, "result_2": 16, "map_winner": 2, "rank_1": 68, "rank_2": 88, "event_id": 3971, "match_id": 2325851}
{"event_timestamp": "2026-05-11 19:51:14", "date": "2018-08-20", "team_1": "EURONICS", "team_2": "Sharks", "map": "Train", "result_1": 11, "result_2": 16, "map_winner": 2, "rank_1": 45, "rank_2": 64, "event_id": 3960, "match_id": 2325834}
{"event_timestamp": "2026-05-11 19:51:14", "date": "2018-08-20", "team_1": "EURONICS", "team_2": "Sharks", "map": "Cache", "result_1": 14, "result_2": 16, "map_winner": 2, "rank_1": 45, "rank_2": 64, "event_id": 3960, "match_id": 2325834}
{"event_timestamp": "2026-05-11 19:51:14", "date": "2018-08-20", "team_1": "PACT", "team_2": "Tricked", "map": "Mirage", "result_1": 12, "result_2": 16, "map_winner": 2, "rank_1": 93, "rank_2": 78, "event_id": 3977, "match_id": 2325783}
{"event_timestamp": "2026-05-11 19:51:14", "date": "2018-08-20", "team_1": "fnatic Academy", "team_2": "Bpro", "map": "Cache", "result_1": 1, "result_2": 16, "map_winner": 2, "rank_1": 72, "rank_2": 98, "event_id": 3946, "match_id": 2325508}
{"event_timestamp": "2026-05-11 19:51:14", "date": "2018-08-20", "team_1": "fnatic Academy", "team_2": "Bpro", "map": "Inferno", "result_1": 14, "result_2": 16, "map_winner": 2, "rank_1": 72, "rank_2": 98, "event_id": 3946, "match_id": 2325508}
{"event_timestamp": "2026-05-11 19:51:14", "date": "2018-08-20", "team_1": "Valiance", "team_2": "Vexed", "map": "Mirage", "result_1": 16, "result_2": 8, "map_winner": 1, "rank_1": 55, "rank_2": 124, "event_id": 3971, "match_id": 2325850}
{"event_timestamp": "2026-05-11 19:51:14", "date": "2018-08-19", "team_1": "MVP PK", "team_2": "SCARZ Absolute", "map": "Mirage", "result_1": 16, "result_2": 14, "map_winner": 1, "rank_1": 73, "rank_2": 61, "event_id": 3970, "match_id": 2325820}
{"event_timestamp": "2026-05-11 19:51:14", "date": "2018-08-19", "team_1": "BOOT-d[S]", "team_2": "SCARZ Absolute", "map": "Inferno", "result_1": 16, "result_2": 14, "map_winner": 1, "rank_1": 40, "rank_2": 61, "event_id": 3970, "match_id": 2325817}
{"event_timestamp": "2026-05-11 19:51:14", "date": "2018-08-19", "team_1": "Unique", "team_2": "pro100", "map": "Cache", "result_1": 9, "result_2": 16, "map_winner": 2, "rank_1": 99, "rank_2": 46, "event_id": 3959, "match_id": 2325800}
{"event_timestamp": "2026-05-11 19:51:14", "date": "2018-08-19", "team_1": "Unique", "team_2": "pro100", "map": "Mirage", "result_1": 11, "result_2": 16, "map_winner": 2, "rank_1": 99, "rank_2": 46, "event_id": 3959, "match_id": 2325800}
{"event_timestamp": "2026-05-11 19:51:14", "date": "2018-08-19", "team_1": "MVP PK", "team_2": "SCARZ Absolute", "map": "Nuke", "result_1": 16, "result_2": 6, "map_winner": 1, "rank_1": 73, "rank_2": 61, "event_id": 3970, "match_id": 2325820}
{"event_timestamp": "2026-05-11 19:51:14", "date": "2018-08-19", "team_1": "AVANGAR", "team_2": "WINside", "map": "Cache", "result_1": 16, "result_2": 1, "map_winner": 1, "rank_1": 33, "rank_2": 165, "event_id": 3939, "match_id": 2325822}
{"event_timestamp": "2026-05-11 19:51:14", "date": "2018-08-19", "team_1": "BOOT-d[S]", "team_2": "TNC", "map": "Nuke", "result_1": 16, "result_2": 1, "map_winner": 1, "rank_1": 40, "rank_2": 170, "event_id": 3970, "match_id": 2325821}
{"event_timestamp": "2026-05-11 19:51:14", "date": "2018-08-19", "team_1": "BOOT-d[S]", "team_2": "TNC", "map": "Inferno", "result_1": 16, "result_2": 5, "map_winner": 1, "rank_1": 40, "rank_2": 170, "event_id": 3970, "match_id": 2325821}
{"event_timestamp": "2026-05-11 19:51:14", "date": "2018-08-19", "team_1": "AVANGAR", "team_2": "WINside", "map": "Mirage", "result_1": 16, "result_2": 10, "map_winner": 1, "rank_1": 33, "rank_2": 165, "event_id": 3939, "match_id": 2325822}
{"event_timestamp": "2026-05-11 19:51:14", "date": "2018-08-19", "team_1": "AVANGAR", "team_2": "WINside", "map": "Train", "result_1": 16, "result_2": 9, "map_winner": 1, "rank_1": 33, "rank_2": 165, "event_id": 3939, "match_id": 2325822}
{"event_timestamp": "2026-05-11 19:51:14", "date": "2018-08-19", "team_1": "Flash", "team_2": "5POWER", "map": "Overpass", "result_1": 16, "result_2": 14, "map_winner": 1, "rank_1": 86, "rank_2": 60, "event_id": 3970, "match_id": 2325816}
{"event_timestamp": "2026-05-11 19:51:14", "date": "2018-08-19", "team_1": "BOOT-d[S]", "team_2": "SCARZ Absolute", "map": "Mirage", "result_1": 14, "result_2": 16, "map_winner": 2, "rank_1": 40, "rank_2": 61, "event_id": 3970, "match_id": 2325817}
{"event_timestamp": "2026-05-11 19:51:14", "date": "2018-08-19", "team_1": "CyberZen", "team_2": "Flash", "map": "Train", "result_1": 16, "result_2": 9, "map_winner": 1, "rank_1": 97, "rank_2": 86, "event_id": 3937, "match_id": 2325733}
{"event_timestamp": "2026-05-11 19:51:14", "date": "2018-08-19", "team_1": "Flash", "team_2": "5POWER", "map": "Mirage", "result_1": 16, "result_2": 13, "map_winner": 1, "rank_1": 86, "rank_2": 60, "event_id": 3970, "match_id": 2325816}
{"event_timestamp": "2026-05-11 19:51:14", "date": "2018-08-19", "team_1": "TNC", "team_2": "MVP PK", "map": "Cache", "result_1": 6, "result_2": 16, "map_winner": 2, "rank_1": 170, "rank_2": 73, "event_id": 3970, "match_id": 2325818}
{"event_timestamp": "2026-05-11 19:51:14", "date": "2018-08-19", "team_1": "TNC", "team_2": "MVP PK", "map": "Inferno", "result_1": 15, "result_2": 19, "map_winner": 2, "rank_1": 170, "rank_2": 73, "event_id": 3970, "match_id": 2325818}
{"event_timestamp": "2026-05-11 19:51:14", "date": "2018-08-19", "team_1": "GOSU", "team_2": "EHOME", "map": "Overpass", "result_1": 5, "result_2": 16, "map_winner": 2, "rank_1": 127, "rank_2": 123, "event_id": 3937, "match_id": 2325731}
{"event_timestamp": "2026-05-11 19:51:14", "date": "2018-08-19", "team_1": "GOSU", "team_2": "EHOME", "map": "Inferno", "result_1": 13, "result_2": 16, "map_winner": 2, "rank_1": 127, "rank_2": 123, "event_id": 3937, "match_id": 2325731}
{"event_timestamp": "2026-05-11 19:51:14", "date": "2018-08-19", "team_1": "CyberZen", "team_2": "Flash", "map": "Mirage", "result_1": 16, "result_2": 10, "map_winner": 1, "rank_1": 97, "rank_2": 86, "event_id": 3937, "match_id": 2325733}
{"event_timestamp": "2026-05-11 19:51:14", "date": "2018-08-19", "team_1": "FriendlyFire", "team_2": "3DMAX", "map": "Inferno", "result_1": 9, "result_2": 16, "map_winner": 2, "rank_1": 75, "rank_2": 36, "event_id": 3992, "match_id": 2325825}
{"event_timestamp": "2026-05-11 19:51:14", "date": "2018-08-19", "team_1": "INTZ", "team_2": "DETONA", "map": "Dust2", "result_1": 16, "result_2": 8, "map_winner": 1, "rank_1": 190, "rank_2": 219, "event_id": 3955, "match_id": 2325777}
{"event_timestamp": "2026-05-11 19:51:14", "date": "2018-08-19", "team_1": "INTZ", "team_2": "DETONA", "map": "Cache", "result_1": 13, "result_2": 16, "map_winner": 2, "rank_1": 190, "rank_2": 219, "event_id": 3955, "match_id": 2325777}
{"event_timestamp": "2026-05-11 19:51:14", "date": "2018-08-19", "team_1": "INTZ", "team_2": "DETONA", "map": "Mirage", "result_1": 5, "result_2": 16, "map_winner": 2, "rank_1": 190, "rank_2": 219, "event_id": 3955, "match_id": 2325777}
{"event_timestamp": "2026-05-11 19:51:14", "date": "2018-08-19", "team_1": "AVANT", "team_2": "Dynasty", "map": "Mirage", "result_1": 16, "result_2": 14, "map_winner": 1, "rank_1": 133, "rank_2": 183, "event_id": 3989, "match_id": 2325998}
{"event_timestamp": "2026-05-11 19:51:14", "date": "2018-08-19", "team_1": "Ground Zero", "team_2": "AVANT", "map": "Inferno", "result_1": 14, "result_2": 16, "map_winner": 2, "rank_1": 160, "rank_2": 133, "event_id": 3989, "match_id": 2325999}
{"event_timestamp": "2026-05-11 19:51:14", "date": "2018-08-19", "team_1": "warmup", "team_2": "Smoke Criminals", "map": "Inferno", "result_1": 8, "result_2": 16, "map_winner": 2, "rank_1": 104, "rank_2": 83, "event_id": 3992, "match_id": 2325824}
{"event_timestamp": "2026-05-11 19:51:14", "date": "2018-08-19", "team_1": "BOOT-d[S]", "team_2": "SCARZ Absolute", "map": "Cache", "result_1": 13, "result_2": 16, "map_winner": 2, "rank_1": 40, "rank_2": 61, "event_id": 3970, "match_id": 2325817}
{"event_timestamp": "2026-05-11 19:51:14", "date": "2018-08-19", "team_1": "fnatic Academy", "team_2": "Royal Bandits", "map": "Mirage", "result_1": 7, "result_2": 16, "map_winner": 2, "rank_1": 72, "rank_2": 119, "event_id": 3992, "match_id": 2325826}
{"event_timestamp": "2026-05-11 19:51:14", "date": "2018-08-19", "team_1": "WINside", "team_2": "EURONICS", "map": "Inferno", "result_1": 10, "result_2": 16, "map_winner": 2, "rank_1": 165, "rank_2": 45, "event_id": 3946, "match_id": 2325626}
{"event_timestamp": "2026-05-11 19:51:14", "date": "2018-08-19", "team_1": "Sharks", "team_2": "Nordavind", "map": "Nuke", "result_1": 7, "result_2": 16, "map_winner": 2, "rank_1": 64, "rank_2": 69, "event_id": 3960, "match_id": 2325794}
{"event_timestamp": "2026-05-11 19:51:14", "date": "2018-08-19", "team_1": "INTZ", "team_2": "ex-Wild", "map": "Train", "result_1": 25, "result_2": 22, "map_winner": 1, "rank_1": 190, "rank_2": 163, "event_id": 3955, "match_id": 2325814}
{"event_timestamp": "2026-05-11 19:51:14", "date": "2018-08-19", "team_1": "INTZ", "team_2": "ex-Wild", "map": "Mirage", "result_1": 12, "result_2": 16, "map_winner": 2, "rank_1": 190, "rank_2": 163, "event_id": 3955, "match_id": 2325814}
{"event_timestamp": "2026-05-11 19:51:14", "date": "2018-08-19", "team_1": "INTZ", "team_2": "ex-Wild", "map": "Cache", "result_1": 13, "result_2": 16, "map_winner": 2, "rank_1": 190, "rank_2": 163, "event_id": 3955, "match_id": 2325814}
{"event_timestamp": "2026-05-11 19:51:14", "date": "2018-08-19", "team_1": "Taboo", "team_2": "Ground Zero", "map": "Dust2", "result_1": 12, "result_2": 16, "map_winner": 2, "rank_1": 216, "rank_2": 160, "event_id": 3989, "match_id": 2325993}
{"event_timestamp": "2026-05-11 19:51:14", "date": "2018-08-19", "team_1": "Revoltz", "team_2": "PITS", "map": "Inferno", "result_1": 5, "result_2": 16, "map_winner": 2, "rank_1": 299, "rank_2": 227, "event_id": 3781, "match_id": 2325832}
{"event_timestamp": "2026-05-11 19:51:14", "date": "2018-08-19", "team_1": "Revoltz", "team_2": "PITS", "map": "Cache", "result_1": 14, "result_2": 16, "map_winner": 2, "rank_1": 299, "rank_2": 227, "event_id": 3781, "match_id": 2325832}
{"event_timestamp": "2026-05-11 19:51:14", "date": "2018-08-19", "team_1": "HAVU", "team_2": "Bpro", "map": "Dust2", "result_1": 14, "result_2": 16, "map_winner": 2, "rank_1": 74, "rank_2": 98, "event_id": 3960, "match_id": 2325796}
{"event_timestamp": "2026-05-11 19:51:14", "date": "2018-08-19", "team_1": "HAVU", "team_2": "Bpro", "map": "Cache", "result_1": 9, "result_2": 16, "map_winner": 2, "rank_1": 74, "rank_2": 98, "event_id": 3960, "match_id": 2325796}
{"event_timestamp": "2026-05-11 19:51:14", "date": "2018-08-19", "team_1": "WINside", "team_2": "EURONICS", "map": "Mirage", "result_1": 16, "result_2": 10, "map_winner": 1, "rank_1": 165, "rank_2": 45, "event_id": 3946, "match_id": 2325626}
{"event_timestamp": "2026-05-11 19:51:14", "date": "2018-08-19", "team_1": "Santos", "team_2": "Isurus", "map": "Inferno", "result_1": 22, "result_2": 20, "map_winner": 1, "rank_1": 223, "rank_2": 194, "event_id": 3771, "match_id": 2325802}
{"event_timestamp": "2026-05-11 19:51:14", "date": "2018-08-19", "team_1": "WINside", "team_2": "EURONICS", "map": "Overpass", "result_1": 10, "result_2": 16, "map_winner": 2, "rank_1": 165, "rank_2": 45, "event_id": 3946, "match_id": 2325626}
{"event_timestamp": "2026-05-11 19:51:14", "date": "2018-08-19", "team_1": "unknown", "team_2": "Bpro", "map": "Nuke", "result_1": 13, "result_2": 16, "map_winner": 2, "rank_1": 150, "rank_2": 98, "event_id": 3910, "match_id": 2325631}
{"event_timestamp": "2026-05-11 19:51:14", "date": "2018-08-19", "team_1": "Sharks", "team_2": "Nordavind", "map": "Train", "result_1": 7, "result_2": 16, "map_winner": 2, "rank_1": 64, "rank_2": 69, "event_id": 3960, "match_id": 2325794}
{"event_timestamp": "2026-05-11 19:51:14", "date": "2018-08-19", "team_1": "Tricked", "team_2": "x-kom", "map": "Inferno", "result_1": 16, "result_2": 9, "map_winner": 1, "rank_1": 78, "rank_2": 88, "event_id": 3960, "match_id": 2325795}
{"event_timestamp": "2026-05-11 19:51:14", "date": "2018-08-19", "team_1": "Chaos", "team_2": "AGO", "map": "Train", "result_1": 8, "result_2": 16, "map_winner": 2, "rank_1": 76, "rank_2": 29, "event_id": 3992, "match_id": 2325827}
{"event_timestamp": "2026-05-11 19:51:14", "date": "2018-08-19", "team_1": "Revoltz", "team_2": "PITS", "map": "Dust2", "result_1": 16, "result_2": 13, "map_winner": 1, "rank_1": 299, "rank_2": 227, "event_id": 3781, "match_id": 2325798}
{"event_timestamp": "2026-05-11 19:51:14", "date": "2018-08-19", "team_1": "Sharks", "team_2": "Nordavind", "map": "Mirage", "result_1": 16, "result_2": 13, "map_winner": 1, "rank_1": 64, "rank_2": 69, "event_id": 3960, "match_id": 2325794}
{"event_timestamp": "2026-05-11 19:51:14", "date": "2018-08-19", "team_1": "unknown", "team_2": "Bpro", "map": "Cache", "result_1": 11, "result_2": 16, "map_winner": 2, "rank_1": 150, "rank_2": 98, "event_id": 3910, "match_id": 2325631}
{"event_timestamp": "2026-05-11 19:51:14", "date": "2018-08-19", "team_1": "Wild", "team_2": "W7M", "map": "Inferno", "result_1": 14, "result_2": 16, "map_winner": 2, "rank_1": 136, "rank_2": 197, "event_id": 3771, "match_id": 2325801}
{"event_timestamp": "2026-05-11 19:51:14", "date": "2018-08-19", "team_1": "Tricked", "team_2": "x-kom", "map": "Dust2", "result_1": 5, "result_2": 16, "map_winner": 2, "rank_1": 78, "rank_2": 88, "event_id": 3960, "match_id": 2325795}
{"event_timestamp": "2026-05-11 19:51:14", "date": "2018-08-19", "team_1": "Tricked", "team_2": "x-kom", "map": "Mirage", "result_1": 12, "result_2": 16, "map_winner": 2, "rank_1": 78, "rank_2": 88, "event_id": 3960, "match_id": 2325795}
{"event_timestamp": "2026-05-11 19:51:14", "date": "2018-08-18", "team_1": "Rise and Grind", "team_2": "Dynasty", "map": "Inferno", "result_1": 13, "result_2": 16, "map_winner": 2, "rank_1": 147, "rank_2": 183, "event_id": 3989, "match_id": 2325995}
{"event_timestamp": "2026-05-11 19:51:14", "date": "2018-08-18", "team_1": "Beyond", "team_2": "Flash", "map": "Cache", "result_1": 16, "result_2": 19, "map_winner": 2, "rank_1": 118, "rank_2": 86, "event_id": 3937, "match_id": 2325730}
{"event_timestamp": "2026-05-11 19:51:14", "date": "2018-08-18", "team_1": "TYLOO", "team_2": "CyberZen", "map": "Train", "result_1": 16, "result_2": 6, "map_winner": 1, "rank_1": 12, "rank_2": 97, "event_id": 3937, "match_id": 2325712}
{"event_timestamp": "2026-05-11 19:51:14", "date": "2018-08-18", "team_1": "TYLOO", "team_2": "CyberZen", "map": "Inferno", "result_1": 13, "result_2": 16, "map_winner": 2, "rank_1": 12, "rank_2": 97, "event_id": 3937, "match_id": 2325712}
{"event_timestamp": "2026-05-11 19:51:14", "date": "2018-08-18", "team_1": "TYLOO", "team_2": "CyberZen", "map": "Mirage", "result_1": 16, "result_2": 6, "map_winner": 1, "rank_1": 12, "rank_2": 97, "event_id": 3937, "match_id": 2325712}
{"event_timestamp": "2026-05-11 19:51:14", "date": "2018-08-18", "team_1": "BOOT-d[S]", "team_2": "MVP PK", "map": "Mirage", "result_1": 4, "result_2": 16, "map_winner": 2, "rank_1": 40, "rank_2": 73, "event_id": 3937, "match_id": 2325713}
{"event_timestamp": "2026-05-11 19:51:14", "date": "2018-08-18", "team_1": "BOOT-d[S]", "team_2": "MVP PK", "map": "Nuke", "result_1": 12, "result_2": 16, "map_winner": 2, "rank_1": 40, "rank_2": 73, "event_id": 3937, "match_id": 2325713}
{"event_timestamp": "2026-05-11 19:51:14", "date": "2018-08-18", "team_1": "TYLOO", "team_2": "MVP PK", "map": "Train", "result_1": 16, "result_2": 8, "map_winner": 1, "rank_1": 12, "rank_2": 73, "event_id": 3937, "match_id": 2325714}