{"event_timestamp": "2026-05-11 19:53:28", "date": "2018-01-08", "team_1": "LANg0ds", "team_2": "ALTERNATE aTTaX", "map": "Overpass", "result_1": 11, "result_2": 16, "map_winner": 2, "rank_1": 142, "rank_2": 36, "event_id": 3356, "match_id": 2318457}
{"event_timestamp": "2026-05-11 19:53:28", "date": "2018-01-08", "team_1": "ALTERNATE aTTaX", "team_2": "LANg0ds", "map": "Inferno", "result_1": 16, "result_2": 7, "map_winner": 1, "rank_1": 36, "rank_2": 142, "event_id": 3356, "match_id": 2318458}
{"event_timestamp": "2026-05-11 19:53:28", "date": "2018-01-08", "team_1": "Rogue", "team_2": "Ghost", "map": "Overpass", "result_1": 7, "result_2": 16, "map_winner": 2, "rank_1": 79, "rank_2": 92, "event_id": 3360, "match_id": 2318420}
{"event_timestamp": "2026-05-11 19:53:28", "date": "2018-01-08", "team_1": "Rogue", "team_2": "Ghost", "map": "Cobblestone", "result_1": 11, "result_2": 16, "map_winner": 2, "rank_1": 79, "rank_2": 92, "event_id": 3360, "match_id": 2318420}
{"event_timestamp": "2026-05-11 19:53:28", "date": "2018-01-08", "team_1": "Rise Nation", "team_2": "Rogue", "map": "Mirage", "result_1": 12, "result_2": 16, "map_winner": 2, "rank_1": 34, "rank_2": 75, "event_id": 3360, "match_id": 2318421}
{"event_timestamp": "2026-05-11 19:53:28", "date": "2018-01-08", "team_1": "Rise Nation", "team_2": "Rogue", "map": "Inferno", "result_1": 17, "result_2": 19, "map_winner": 2, "rank_1": 34, "rank_2": 75, "event_id": 3360, "match_id": 2318421}
{"event_timestamp": "2026-05-11 19:53:28", "date": "2018-01-07", "team_1": "RONIN", "team_2": "Etherian", "map": "Overpass", "result_1": 6, "result_2": 16, "map_winner": 2, "rank_1": 130, "rank_2": 110, "event_id": 3404, "match_id": 2318453}
{"event_timestamp": "2026-05-11 19:53:28", "date": "2018-01-07", "team_1": "Masterminds", "team_2": "Athletico", "map": "Cobblestone", "result_1": 7, "result_2": 16, "map_winner": 2, "rank_1": 204, "rank_2": 89, "event_id": 3433, "match_id": 2318446}
{"event_timestamp": "2026-05-11 19:53:28", "date": "2018-01-07", "team_1": "Ardeont", "team_2": "Lucid Dream", "map": "Overpass", "result_1": 16, "result_2": 12, "map_winner": 1, "rank_1": 210, "rank_2": 282, "event_id": 3436, "match_id": 2318450}
{"event_timestamp": "2026-05-11 19:53:28", "date": "2018-01-07", "team_1": "Space Soldiers", "team_2": "AGO", "map": "Train", "result_1": 12, "result_2": 16, "map_winner": 2, "rank_1": 24, "rank_2": 21, "event_id": 3314, "match_id": 2318418}
{"event_timestamp": "2026-05-11 19:53:28", "date": "2018-01-07", "team_1": "Space Soldiers", "team_2": "AGO", "map": "Mirage", "result_1": 18, "result_2": 22, "map_winner": 2, "rank_1": 24, "rank_2": 21, "event_id": 3314, "match_id": 2318418}
{"event_timestamp": "2026-05-11 19:53:28", "date": "2018-01-07", "team_1": "Swole Patrol", "team_2": "Blackwoodproductions", "map": "Inferno", "result_1": 16, "result_2": 3, "map_winner": 1, "rank_1": 87, "rank_2": 136, "event_id": 3404, "match_id": 2318452}
{"event_timestamp": "2026-05-11 19:53:28", "date": "2018-01-07", "team_1": "Swole Patrol", "team_2": "Blackwoodproductions", "map": "Mirage", "result_1": 16, "result_2": 12, "map_winner": 1, "rank_1": 87, "rank_2": 136, "event_id": 3404, "match_id": 2318452}
{"event_timestamp": "2026-05-11 19:53:28", "date": "2018-01-07", "team_1": "RONIN", "team_2": "Etherian", "map": "Inferno", "result_1": 6, "result_2": 16, "map_winner": 2, "rank_1": 130, "rank_2": 110, "event_id": 3404, "match_id": 2318453}
{"event_timestamp": "2026-05-11 19:53:28", "date": "2018-01-07", "team_1": "Etherian", "team_2": "Swole Patrol", "map": "Mirage", "result_1": 6, "result_2": 16, "map_winner": 2, "rank_1": 110, "rank_2": 87, "event_id": 3404, "match_id": 2318454}
{"event_timestamp": "2026-05-11 19:53:28", "date": "2018-01-07", "team_1": "Space Soldiers", "team_2": "Natus Vincere", "map": "Train", "result_1": 8, "result_2": 16, "map_winner": 2, "rank_1": 24, "rank_2": 14, "event_id": 3359, "match_id": 2318402}
{"event_timestamp": "2026-05-11 19:53:28", "date": "2018-01-07", "team_1": "Space Soldiers", "team_2": "Natus Vincere", "map": "Mirage", "result_1": 16, "result_2": 14, "map_winner": 1, "rank_1": 24, "rank_2": 14, "event_id": 3359, "match_id": 2318402}
{"event_timestamp": "2026-05-11 19:53:28", "date": "2018-01-07", "team_1": "Space Soldiers", "team_2": "Natus Vincere", "map": "Inferno", "result_1": 10, "result_2": 16, "map_winner": 2, "rank_1": 24, "rank_2": 14, "event_id": 3359, "match_id": 2318402}
{"event_timestamp": "2026-05-11 19:53:28", "date": "2018-01-07", "team_1": "Etherian", "team_2": "Swole Patrol", "map": "Train", "result_1": 9, "result_2": 16, "map_winner": 2, "rank_1": 110, "rank_2": 87, "event_id": 3404, "match_id": 2318454}
{"event_timestamp": "2026-05-11 19:53:28", "date": "2018-01-07", "team_1": "RONIN", "team_2": "Blackwoodproductions", "map": "Mirage", "result_1": 18, "result_2": 22, "map_winner": 2, "rank_1": 130, "rank_2": 136, "event_id": 3404, "match_id": 2318455}
{"event_timestamp": "2026-05-11 19:53:28", "date": "2018-01-06", "team_1": "ViCi", "team_2": "New4", "map": "Mirage", "result_1": 13, "result_2": 16, "map_winner": 2, "rank_1": 50, "rank_2": 237, "event_id": 3468, "match_id": 2318445}
{"event_timestamp": "2026-05-11 19:53:28", "date": "2018-01-06", "team_1": "Chiefs", "team_2": "Rise Nation", "map": "Overpass", "result_1": 19, "result_2": 17, "map_winner": 1, "rank_1": 54, "rank_2": 33, "event_id": 3314, "match_id": 2318412}
{"event_timestamp": "2026-05-11 19:53:28", "date": "2018-01-06", "team_1": "Ghost Academy", "team_2": "GX", "map": "Mirage", "result_1": 16, "result_2": 13, "map_winner": 1, "rank_1": 102, "rank_2": 71, "event_id": 3314, "match_id": 2318413}
{"event_timestamp": "2026-05-11 19:53:28", "date": "2018-01-06", "team_1": "MVP PK", "team_2": "ViCi", "map": "Train", "result_1": 16, "result_2": 9, "map_winner": 1, "rank_1": 59, "rank_2": 50, "event_id": 3490, "match_id": 2318443}
{"event_timestamp": "2026-05-11 19:53:28", "date": "2018-01-06", "team_1": "MVP PK", "team_2": "ViCi", "map": "Inferno", "result_1": 6, "result_2": 16, "map_winner": 2, "rank_1": 59, "rank_2": 50, "event_id": 3490, "match_id": 2318443}
{"event_timestamp": "2026-05-11 19:53:28", "date": "2018-01-06", "team_1": "MVP PK", "team_2": "ViCi", "map": "Overpass", "result_1": 16, "result_2": 12, "map_winner": 1, "rank_1": 59, "rank_2": 50, "event_id": 3490, "match_id": 2318443}
{"event_timestamp": "2026-05-11 19:53:28", "date": "2018-01-06", "team_1": "ViCi", "team_2": "New4", "map": "Train", "result_1": 16, "result_2": 13, "map_winner": 1, "rank_1": 50, "rank_2": 237, "event_id": 3468, "match_id": 2318445}
{"event_timestamp": "2026-05-11 19:53:28", "date": "2018-01-06", "team_1": "Space Soldiers", "team_2": "Chiefs", "map": "Cobblestone", "result_1": 16, "result_2": 9, "map_winner": 1, "rank_1": 24, "rank_2": 54, "event_id": 3314, "match_id": 2318414}
{"event_timestamp": "2026-05-11 19:53:28", "date": "2018-01-06", "team_1": "ViCi", "team_2": "New4", "map": "Inferno", "result_1": 16, "result_2": 9, "map_winner": 1, "rank_1": 50, "rank_2": 237, "event_id": 3468, "match_id": 2318445}
{"event_timestamp": "2026-05-11 19:53:28", "date": "2018-01-06", "team_1": "eXtatus", "team_2": "Space Soldiers", "map": "Inferno", "result_1": 13, "result_2": 16, "map_winner": 2, "rank_1": 38, "rank_2": 24, "event_id": 3314, "match_id": 2318416}
{"event_timestamp": "2026-05-11 19:53:28", "date": "2018-01-06", "team_1": "eXtatus", "team_2": "Space Soldiers", "map": "Mirage", "result_1": 9, "result_2": 16, "map_winner": 2, "rank_1": 38, "rank_2": 24, "event_id": 3314, "match_id": 2318416}
{"event_timestamp": "2026-05-11 19:53:28", "date": "2018-01-06", "team_1": "eXtatus", "team_2": "Space Soldiers", "map": "Overpass", "result_1": 16, "result_2": 12, "map_winner": 1, "rank_1": 38, "rank_2": 24, "event_id": 3314, "match_id": 2318416}
{"event_timestamp": "2026-05-11 19:53:28", "date": "2018-01-06", "team_1": "AGO", "team_2": "Ghost Academy", "map": "Overpass", "result_1": 16, "result_2": 5, "map_winner": 1, "rank_1": 21, "rank_2": 102, "event_id": 3314, "match_id": 2318417}
{"event_timestamp": "2026-05-11 19:53:28", "date": "2018-01-06", "team_1": "AGO", "team_2": "Ghost Academy", "map": "Train", "result_1": 16, "result_2": 2, "map_winner": 1, "rank_1": 21, "rank_2": 102, "event_id": 3314, "match_id": 2318417}
{"event_timestamp": "2026-05-11 19:53:28", "date": "2018-01-06", "team_1": "SoaR", "team_2": "Ghost Academy", "map": "Inferno", "result_1": 19, "result_2": 22, "map_winner": 2, "rank_1": 52, "rank_2": 102, "event_id": 3314, "match_id": 2318415}
{"event_timestamp": "2026-05-11 19:53:28", "date": "2018-01-05", "team_1": "ViCi", "team_2": "Red Wolf", "map": "Inferno", "result_1": 16, "result_2": 8, "map_winner": 1, "rank_1": 50, "rank_2": 139, "event_id": 3490, "match_id": 2318439}
{"event_timestamp": "2026-05-11 19:53:28", "date": "2018-01-05", "team_1": "Chiefs", "team_2": "AGO", "map": "Train", "result_1": 5, "result_2": 16, "map_winner": 2, "rank_1": 54, "rank_2": 21, "event_id": 3314, "match_id": 2318406}
{"event_timestamp": "2026-05-11 19:53:28", "date": "2018-01-05", "team_1": "Red Wolf", "team_2": "ViCi", "map": "Inferno", "result_1": 6, "result_2": 16, "map_winner": 2, "rank_1": 139, "rank_2": 50, "event_id": 3468, "match_id": 2318436}
{"event_timestamp": "2026-05-11 19:53:28", "date": "2018-01-05", "team_1": "ViCi", "team_2": "Red Wolf", "map": "Cobblestone", "result_1": 16, "result_2": 4, "map_winner": 1, "rank_1": 50, "rank_2": 139, "event_id": 3490, "match_id": 2318439}
{"event_timestamp": "2026-05-11 19:53:28", "date": "2018-01-05", "team_1": "ViCi", "team_2": "Red Wolf", "map": "Mirage", "result_1": 10, "result_2": 16, "map_winner": 2, "rank_1": 50, "rank_2": 139, "event_id": 3490, "match_id": 2318439}
{"event_timestamp": "2026-05-11 19:53:28", "date": "2018-01-05", "team_1": "Space Soldiers", "team_2": "Rise Nation", "map": "Mirage", "result_1": 16, "result_2": 7, "map_winner": 1, "rank_1": 24, "rank_2": 33, "event_id": 3314, "match_id": 2318407}
{"event_timestamp": "2026-05-11 19:53:28", "date": "2018-01-05", "team_1": "GX", "team_2": "eXtatus", "map": "Cache", "result_1": 11, "result_2": 16, "map_winner": 2, "rank_1": 71, "rank_2": 38, "event_id": 3314, "match_id": 2318409}
{"event_timestamp": "2026-05-11 19:53:28", "date": "2018-01-05", "team_1": "AGO", "team_2": "Space Soldiers", "map": "Cobblestone", "result_1": 16, "result_2": 11, "map_winner": 1, "rank_1": 21, "rank_2": 24, "event_id": 3314, "match_id": 2318410}
{"event_timestamp": "2026-05-11 19:53:28", "date": "2018-01-05", "team_1": "SoaR", "team_2": "eXtatus", "map": "Train", "result_1": 9, "result_2": 16, "map_winner": 2, "rank_1": 52, "rank_2": 38, "event_id": 3314, "match_id": 2318411}
{"event_timestamp": "2026-05-11 19:53:28", "date": "2018-01-05", "team_1": "Ghost Academy", "team_2": "SoaR", "map": "Mirage", "result_1": 24, "result_2": 28, "map_winner": 2, "rank_1": 102, "rank_2": 52, "event_id": 3314, "match_id": 2318408}
{"event_timestamp": "2026-05-11 19:53:28", "date": "2018-01-04", "team_1": "Rise Nation", "team_2": "SoaR", "map": "Mirage", "result_1": 16, "result_2": 19, "map_winner": 2, "rank_1": 33, "rank_2": 52, "event_id": 3366, "match_id": 2318401}
{"event_timestamp": "2026-05-11 19:53:28", "date": "2018-01-04", "team_1": "Rise Nation", "team_2": "SoaR", "map": "Inferno", "result_1": 16, "result_2": 7, "map_winner": 1, "rank_1": 33, "rank_2": 52, "event_id": 3366, "match_id": 2318401}
{"event_timestamp": "2026-05-11 19:53:28", "date": "2018-01-04", "team_1": "Rise Nation", "team_2": "SoaR", "map": "Train", "result_1": 12, "result_2": 16, "map_winner": 2, "rank_1": 33, "rank_2": 52, "event_id": 3366, "match_id": 2318401}
{"event_timestamp": "2026-05-11 19:53:28", "date": "2018-01-04", "team_1": "eXtatus", "team_2": "AGO", "map": "Mirage", "result_1": 14, "result_2": 16, "map_winner": 2, "rank_1": 38, "rank_2": 21, "event_id": 3365, "match_id": 2318400}
{"event_timestamp": "2026-05-11 19:53:28", "date": "2018-01-04", "team_1": "eXtatus", "team_2": "AGO", "map": "Train", "result_1": 11, "result_2": 16, "map_winner": 2, "rank_1": 38, "rank_2": 21, "event_id": 3365, "match_id": 2318400}
{"event_timestamp": "2026-05-11 19:53:28", "date": "2018-01-04", "team_1": "New4", "team_2": "Red Wolf", "map": "Cache", "result_1": 16, "result_2": 1, "map_winner": 1, "rank_1": 237, "rank_2": 139, "event_id": 3468, "match_id": 2318426}
{"event_timestamp": "2026-05-11 19:53:28", "date": "2018-01-04", "team_1": "ViCi", "team_2": "New4", "map": "Inferno", "result_1": 16, "result_2": 6, "map_winner": 1, "rank_1": 50, "rank_2": 237, "event_id": 3468, "match_id": 2318425}
{"event_timestamp": "2026-05-11 19:53:28", "date": "2017-12-31", "team_1": "MVP PK", "team_2": "Eclipse", "map": "Nuke", "result_1": 13, "result_2": 16, "map_winner": 2, "rank_1": 69, "rank_2": 65, "event_id": 3475, "match_id": 2318397}
{"event_timestamp": "2026-05-11 19:53:28", "date": "2017-12-31", "team_1": "MVP PK", "team_2": "Eclipse", "map": "Mirage", "result_1": 16, "result_2": 9, "map_winner": 1, "rank_1": 69, "rank_2": 65, "event_id": 3475, "match_id": 2318397}
{"event_timestamp": "2026-05-11 19:53:28", "date": "2017-12-31", "team_1": "MVP PK", "team_2": "Eclipse", "map": "Inferno", "result_1": 16, "result_2": 6, "map_winner": 1, "rank_1": 69, "rank_2": 65, "event_id": 3475, "match_id": 2318397}
{"event_timestamp": "2026-05-11 19:53:28", "date": "2017-12-31", "team_1": "TYLOO", "team_2": "MVP PK", "map": "Mirage", "result_1": 19, "result_2": 15, "map_winner": 1, "rank_1": 39, "rank_2": 69, "event_id": 3475, "match_id": 2318399}
{"event_timestamp": "2026-05-11 19:53:28", "date": "2017-12-31", "team_1": "Flash", "team_2": "MVP PK", "map": "Mirage", "result_1": 8, "result_2": 16, "map_winner": 2, "rank_1": 59, "rank_2": 69, "event_id": 3475, "match_id": 2318398}
{"event_timestamp": "2026-05-11 19:53:28", "date": "2017-12-31", "team_1": "Flash", "team_2": "MVP PK", "map": "Inferno", "result_1": 14, "result_2": 16, "map_winner": 2, "rank_1": 59, "rank_2": 69, "event_id": 3475, "match_id": 2318398}
{"event_timestamp": "2026-05-11 19:53:28", "date": "2017-12-31", "team_1": "TYLOO", "team_2": "MVP PK", "map": "Overpass", "result_1": 16, "result_2": 7, "map_winner": 1, "rank_1": 39, "rank_2": 69, "event_id": 3475, "match_id": 2318399}
{"event_timestamp": "2026-05-11 19:53:28", "date": "2017-12-30", "team_1": "Flash", "team_2": "Eclipse", "map": "Overpass", "result_1": 16, "result_2": 8, "map_winner": 1, "rank_1": 59, "rank_2": 65, "event_id": 3475, "match_id": 2318395}
{"event_timestamp": "2026-05-11 19:53:28", "date": "2017-12-30", "team_1": "Isurus", "team_2": "Hafnet", "map": "Cobblestone", "result_1": 7, "result_2": 16, "map_winner": 2, "rank_1": 143, "rank_2": 185, "event_id": 3423, "match_id": 2318385}
{"event_timestamp": "2026-05-11 19:53:28", "date": "2017-12-30", "team_1": "Isurus", "team_2": "Hafnet", "map": "Mirage", "result_1": 16, "result_2": 11, "map_winner": 1, "rank_1": 143, "rank_2": 185, "event_id": 3423, "match_id": 2318385}
{"event_timestamp": "2026-05-11 19:53:28", "date": "2017-12-30", "team_1": "TYLOO", "team_2": "MVP PK", "map": "Train", "result_1": 16, "result_2": 6, "map_winner": 1, "rank_1": 39, "rank_2": 69, "event_id": 3475, "match_id": 2318394}
{"event_timestamp": "2026-05-11 19:53:28", "date": "2017-12-30", "team_1": "TYLOO", "team_2": "MVP PK", "map": "Mirage", "result_1": 16, "result_2": 8, "map_winner": 1, "rank_1": 39, "rank_2": 69, "event_id": 3475, "match_id": 2318394}
{"event_timestamp": "2026-05-11 19:53:28", "date": "2017-12-30", "team_1": "Isurus", "team_2": "Hafnet", "map": "Inferno", "result_1": 16, "result_2": 14, "map_winner": 1, "rank_1": 143, "rank_2": 185, "event_id": 3423, "match_id": 2318385}
{"event_timestamp": "2026-05-11 19:53:28", "date": "2017-12-30", "team_1": "Flash", "team_2": "Eclipse", "map": "Cobblestone", "result_1": 16, "result_2": 8, "map_winner": 1, "rank_1": 59, "rank_2": 65, "event_id": 3475, "match_id": 2318395}
{"event_timestamp": "2026-05-11 19:53:28", "date": "2017-12-30", "team_1": "TYLOO", "team_2": "Flash", "map": "Cobblestone", "result_1": 16, "result_2": 12, "map_winner": 1, "rank_1": 39, "rank_2": 59, "event_id": 3475, "match_id": 2318396}
{"event_timestamp": "2026-05-11 19:53:28", "date": "2017-12-30", "team_1": "TYLOO", "team_2": "Flash", "map": "Cache", "result_1": 16, "result_2": 10, "map_winner": 1, "rank_1": 39, "rank_2": 59, "event_id": 3475, "match_id": 2318396}
{"event_timestamp": "2026-05-11 19:53:28", "date": "2017-12-30", "team_1": "TYLOO", "team_2": "Flash", "map": "Mirage", "result_1": 14, "result_2": 16, "map_winner": 2, "rank_1": 39, "rank_2": 59, "event_id": 3475, "match_id": 2318396}
{"event_timestamp": "2026-05-11 19:53:28", "date": "2017-12-30", "team_1": "Flash", "team_2": "Eclipse", "map": "Inferno", "result_1": 12, "result_2": 16, "map_winner": 2, "rank_1": 59, "rank_2": 65, "event_id": 3475, "match_id": 2318395}
{"event_timestamp": "2026-05-11 19:53:28", "date": "2017-12-29", "team_1": "Kinguin", "team_2": "HAVU", "map": "Inferno", "result_1": 16, "result_2": 9, "map_winner": 1, "rank_1": 32, "rank_2": 49, "event_id": 3290, "match_id": 2318384}
{"event_timestamp": "2026-05-11 19:53:28", "date": "2017-12-29", "team_1": "Kinguin", "team_2": "HAVU", "map": "Mirage", "result_1": 16, "result_2": 10, "map_winner": 1, "rank_1": 32, "rank_2": 49, "event_id": 3290, "match_id": 2318384}
{"event_timestamp": "2026-05-11 19:53:28", "date": "2017-12-29", "team_1": "BOOT-d[S]", "team_2": "5POWER", "map": "Mirage", "result_1": 16, "result_2": 3, "map_winner": 1, "rank_1": 89, "rank_2": 104, "event_id": 3456, "match_id": 2318264}
{"event_timestamp": "2026-05-11 19:53:28", "date": "2017-12-29", "team_1": "BOOT-d[S]", "team_2": "5POWER", "map": "Train", "result_1": 16, "result_2": 6, "map_winner": 1, "rank_1": 89, "rank_2": 104, "event_id": 3456, "match_id": 2318264}
{"event_timestamp": "2026-05-11 19:53:28", "date": "2017-12-28", "team_1": "5POWER", "team_2": "Recca", "map": "Mirage", "result_1": 16, "result_2": 13, "map_winner": 1, "rank_1": 104, "rank_2": 105, "event_id": 3456, "match_id": 2318262}
{"event_timestamp": "2026-05-11 19:53:28", "date": "2017-12-28", "team_1": "Isurus", "team_2": "Ivyaert", "map": "Train", "result_1": 16, "result_2": 11, "map_winner": 1, "rank_1": 143, "rank_2": 244, "event_id": 3423, "match_id": 2318374}
{"event_timestamp": "2026-05-11 19:53:28", "date": "2017-12-28", "team_1": "Isurus", "team_2": "Ivyaert", "map": "Overpass", "result_1": 16, "result_2": 7, "map_winner": 1, "rank_1": 143, "rank_2": 244, "event_id": 3423, "match_id": 2318374}
{"event_timestamp": "2026-05-11 19:53:28", "date": "2017-12-28", "team_1": "Hafnet", "team_2": "AEON", "map": "Mirage", "result_1": 16, "result_2": 7, "map_winner": 1, "rank_1": 185, "rank_2": 231, "event_id": 3423, "match_id": 2318373}
{"event_timestamp": "2026-05-11 19:53:28", "date": "2017-12-28", "team_1": "Hafnet", "team_2": "AEON", "map": "Overpass", "result_1": 16, "result_2": 11, "map_winner": 1, "rank_1": 185, "rank_2": 231, "event_id": 3423, "match_id": 2318373}
{"event_timestamp": "2026-05-11 19:53:28", "date": "2017-12-28", "team_1": "TYLOO", "team_2": "Eclipse", "map": "Mirage", "result_1": 16, "result_2": 13, "map_winner": 1, "rank_1": 39, "rank_2": 65, "event_id": 3475, "match_id": 2318386}
{"event_timestamp": "2026-05-11 19:53:28", "date": "2017-12-28", "team_1": "Flash", "team_2": "MVP PK", "map": "Overpass", "result_1": 16, "result_2": 12, "map_winner": 1, "rank_1": 59, "rank_2": 69, "event_id": 3475, "match_id": 2318387}
{"event_timestamp": "2026-05-11 19:53:28", "date": "2017-12-28", "team_1": "5POWER", "team_2": "Recca", "map": "Cache", "result_1": 16, "result_2": 6, "map_winner": 1, "rank_1": 104, "rank_2": 105, "event_id": 3456, "match_id": 2318262}
{"event_timestamp": "2026-05-11 19:53:28", "date": "2017-12-28", "team_1": "AGO", "team_2": "pro100", "map": "Overpass", "result_1": 16, "result_2": 14, "map_winner": 1, "rank_1": 20, "rank_2": 46, "event_id": 3333, "match_id": 2318362}
{"event_timestamp": "2026-05-11 19:53:28", "date": "2017-12-28", "team_1": "mousesports", "team_2": "Vega Squadron", "map": "Inferno", "result_1": 16, "result_2": 14, "map_winner": 1, "rank_1": 8, "rank_2": 25, "event_id": 3421, "match_id": 2318372}
{"event_timestamp": "2026-05-11 19:53:28", "date": "2017-12-28", "team_1": "mousesports", "team_2": "Vega Squadron", "map": "Mirage", "result_1": 16, "result_2": 3, "map_winner": 1, "rank_1": 8, "rank_2": 25, "event_id": 3421, "match_id": 2318372}
{"event_timestamp": "2026-05-11 19:53:28", "date": "2017-12-28", "team_1": "Heroic", "team_2": "mousesports", "map": "Inferno", "result_1": 9, "result_2": 16, "map_winner": 2, "rank_1": 19, "rank_2": 8, "event_id": 3421, "match_id": 2318383}
{"event_timestamp": "2026-05-11 19:53:28", "date": "2017-12-28", "team_1": "Heroic", "team_2": "mousesports", "map": "Cobblestone", "result_1": 4, "result_2": 16, "map_winner": 2, "rank_1": 19, "rank_2": 8, "event_id": 3421, "match_id": 2318383}
{"event_timestamp": "2026-05-11 19:53:28", "date": "2017-12-28", "team_1": "AGO", "team_2": "pro100", "map": "Mirage", "result_1": 16, "result_2": 10, "map_winner": 1, "rank_1": 20, "rank_2": 46, "event_id": 3333, "match_id": 2318362}
{"event_timestamp": "2026-05-11 19:53:28", "date": "2017-12-27", "team_1": "MANS NOT HOT", "team_2": "VenatoreS", "map": "Inferno", "result_1": 16, "result_2": 7, "map_winner": 1, "rank_1": 52, "rank_2": 96, "event_id": 3457, "match_id": 2318349}
{"event_timestamp": "2026-05-11 19:53:28", "date": "2017-12-27", "team_1": "AEON", "team_2": "Licht", "map": "Mirage", "result_1": 16, "result_2": 7, "map_winner": 1, "rank_1": 231, "rank_2": 234, "event_id": 3423, "match_id": 2318371}
{"event_timestamp": "2026-05-11 19:53:28", "date": "2017-12-27", "team_1": "AEON", "team_2": "Licht", "map": "Cobblestone", "result_1": 16, "result_2": 14, "map_winner": 1, "rank_1": 231, "rank_2": 234, "event_id": 3423, "match_id": 2318371}
{"event_timestamp": "2026-05-11 19:53:28", "date": "2017-12-27", "team_1": "MANS NOT HOT", "team_2": "VenatoreS", "map": "Train", "result_1": 16, "result_2": 11, "map_winner": 1, "rank_1": 52, "rank_2": 96, "event_id": 3457, "match_id": 2318349}
{"event_timestamp": "2026-05-11 19:53:28", "date": "2017-12-27", "team_1": "Heroic", "team_2": "Valiance", "map": "Train", "result_1": 16, "result_2": 0, "map_winner": 1, "rank_1": 19, "rank_2": 30, "event_id": 3421, "match_id": 2318360}
{"event_timestamp": "2026-05-11 19:53:28", "date": "2017-12-27", "team_1": "Heroic", "team_2": "Valiance", "map": "Inferno", "result_1": 16, "result_2": 10, "map_winner": 1, "rank_1": 19, "rank_2": 30, "event_id": 3421, "match_id": 2318360}
{"event_timestamp": "2026-05-11 19:53:28", "date": "2017-12-26", "team_1": "Recca", "team_2": "Signature", "map": "Train", "result_1": 16, "result_2": 11, "map_winner": 1, "rank_1": 105, "rank_2": 141, "event_id": 3456, "match_id": 2318217}
{"event_timestamp": "2026-05-11 19:53:28", "date": "2017-12-26", "team_1": "AGO", "team_2": "Vega Squadron", "map": "Inferno", "result_1": 6, "result_2": 16, "map_winner": 2, "rank_1": 20, "rank_2": 25, "event_id": 3421, "match_id": 2318358}
{"event_timestamp": "2026-05-11 19:53:28", "date": "2017-12-26", "team_1": "Recca", "team_2": "Signature", "map": "Mirage", "result_1": 16, "result_2": 9, "map_winner": 1, "rank_1": 105, "rank_2": 141, "event_id": 3456, "match_id": 2318217}
{"event_timestamp": "2026-05-11 19:53:28", "date": "2017-12-26", "team_1": "Recca", "team_2": "Signature", "map": "Cobblestone", "result_1": 14, "result_2": 16, "map_winner": 2, "rank_1": 105, "rank_2": 141, "event_id": 3456, "match_id": 2318217}
{"event_timestamp": "2026-05-11 19:53:28", "date": "2017-12-26", "team_1": "AGO", "team_2": "Vega Squadron", "map": "Train", "result_1": 13, "result_2": 16, "map_winner": 2, "rank_1": 20, "rank_2": 25, "event_id": 3421, "match_id": 2318358}
{"event_timestamp": "2026-05-11 19:53:28", "date": "2017-12-26", "team_1": "mousesports", "team_2": "Spirit", "map": "Nuke", "result_1": 16, "result_2": 8, "map_winner": 1, "rank_1": 8, "rank_2": 40, "event_id": 3421, "match_id": 2318359}
{"event_timestamp": "2026-05-11 19:53:28", "date": "2017-12-26", "team_1": "mousesports", "team_2": "Spirit", "map": "Cache", "result_1": 11, "result_2": 16, "map_winner": 2, "rank_1": 8, "rank_2": 40, "event_id": 3421, "match_id": 2318359}
{"event_timestamp": "2026-05-11 19:53:28", "date": "2017-12-26", "team_1": "mousesports", "team_2": "Spirit", "map": "Mirage", "result_1": 16, "result_2": 9, "map_winner": 1, "rank_1": 8, "rank_2": 40, "event_id": 3421, "match_id": 2318359}
{"event_timestamp": "2026-05-11 19:53:28", "date": "2017-12-25", "team_1": "5POWER", "team_2": "Eclipse", "map": "Mirage", "result_1": 16, "result_2": 10, "map_winner": 1, "rank_1": 72, "rank_2": 63, "event_id": 3477, "match_id": 2318388}
{"event_timestamp": "2026-05-11 19:53:28", "date": "2017-12-25", "team_1": "Codewise Unicorns", "team_2": "Espada", "map": "Inferno", "result_1": 16, "result_2": 13, "map_winner": 1, "rank_1": 319, "rank_2": 152, "event_id": 3472, "match_id": 2318369}
{"event_timestamp": "2026-05-11 19:53:28", "date": "2017-12-25", "team_1": "Spirit", "team_2": "AVANGAR", "map": "Inferno", "result_1": 19, "result_2": 17, "map_winner": 1, "rank_1": 40, "rank_2": 34, "event_id": 3472, "match_id": 2318368}
{"event_timestamp": "2026-05-11 19:53:28", "date": "2017-12-25", "team_1": "Spirit", "team_2": "AVANGAR", "map": "Overpass", "result_1": 16, "result_2": 12, "map_winner": 1, "rank_1": 40, "rank_2": 34, "event_id": 3472, "match_id": 2318368}
{"event_timestamp": "2026-05-11 19:53:28", "date": "2017-12-25", "team_1": "Spirit", "team_2": "AVANGAR", "map": "Cache", "result_1": 13, "result_2": 16, "map_winner": 2, "rank_1": 40, "rank_2": 34, "event_id": 3472, "match_id": 2318368}
{"event_timestamp": "2026-05-11 19:53:28", "date": "2017-12-25", "team_1": "Codewise Unicorns", "team_2": "Espada", "map": "Train", "result_1": 16, "result_2": 5, "map_winner": 1, "rank_1": 319, "rank_2": 152, "event_id": 3472, "match_id": 2318369}
{"event_timestamp": "2026-05-11 19:53:28", "date": "2017-12-25", "team_1": "Spirit", "team_2": "Espada", "map": "Inferno", "result_1": 16, "result_2": 12, "map_winner": 1, "rank_1": 40, "rank_2": 152, "event_id": 3472, "match_id": 2318370}
{"event_timestamp": "2026-05-11 19:53:28", "date": "2017-12-25", "team_1": "Spirit", "team_2": "Espada", "map": "Cache", "result_1": 16, "result_2": 1, "map_winner": 1, "rank_1": 40, "rank_2": 152, "event_id": 3472, "match_id": 2318370}
{"event_timestamp": "2026-05-11 19:53:28", "date": "2017-12-25", "team_1": "Spirit", "team_2": "Espada", "map": "Mirage", "result_1": 8, "result_2": 16, "map_winner": 2, "rank_1": 40, "rank_2": 152, "event_id": 3472, "match_id": 2318370}
{"event_timestamp": "2026-05-11 19:53:28", "date": "2017-12-25", "team_1": "5POWER", "team_2": "Eclipse", "map": "Cobblestone", "result_1": 16, "result_2": 5, "map_winner": 1, "rank_1": 72, "rank_2": 63, "event_id": 3477, "match_id": 2318388}
{"event_timestamp": "2026-05-11 19:53:28", "date": "2017-12-24", "team_1": "NSPR", "team_2": "Beyond", "map": "Cache", "result_1": 16, "result_2": 5, "map_winner": 1, "rank_1": 187, "rank_2": 148, "event_id": 3412, "match_id": 2318347}
{"event_timestamp": "2026-05-11 19:53:28", "date": "2017-12-24", "team_1": "NSPR", "team_2": "MiTH", "map": "Mirage", "result_1": 16, "result_2": 5, "map_winner": 1, "rank_1": 187, "rank_2": 337, "event_id": 3412, "match_id": 2318345}
{"event_timestamp": "2026-05-11 19:53:28", "date": "2017-12-24", "team_1": "NSPR", "team_2": "MiTH", "map": "Inferno", "result_1": 16, "result_2": 11, "map_winner": 1, "rank_1": 187, "rank_2": 337, "event_id": 3412, "match_id": 2318345}
{"event_timestamp": "2026-05-11 19:53:28", "date": "2017-12-24", "team_1": "Signature", "team_2": "Beyond", "map": "Cobblestone", "result_1": 13, "result_2": 16, "map_winner": 2, "rank_1": 141, "rank_2": 148, "event_id": 3412, "match_id": 2318346}
{"event_timestamp": "2026-05-11 19:53:28", "date": "2017-12-24", "team_1": "Signature", "team_2": "Beyond", "map": "Train", "result_1": 8, "result_2": 16, "map_winner": 2, "rank_1": 141, "rank_2": 148, "event_id": 3412, "match_id": 2318346}
{"event_timestamp": "2026-05-11 19:53:28", "date": "2017-12-24", "team_1": "Nemiga", "team_2": "Codewise Unicorns", "map": "Mirage", "result_1": 13, "result_2": 16, "map_winner": 2, "rank_1": 64, "rank_2": 319, "event_id": 3472, "match_id": 2318367}
{"event_timestamp": "2026-05-11 19:53:28", "date": "2017-12-24", "team_1": "NSPR", "team_2": "Beyond", "map": "Inferno", "result_1": 16, "result_2": 8, "map_winner": 1, "rank_1": 187, "rank_2": 148, "event_id": 3412, "match_id": 2318347}
{"event_timestamp": "2026-05-11 19:53:28", "date": "2017-12-24", "team_1": "Nemiga", "team_2": "Codewise Unicorns", "map": "Inferno", "result_1": 14, "result_2": 16, "map_winner": 2, "rank_1": 64, "rank_2": 319, "event_id": 3472, "match_id": 2318367}
{"event_timestamp": "2026-05-11 19:53:28", "date": "2017-12-24", "team_1": "Espada", "team_2": "EPG", "map": "Train", "result_1": 16, "result_2": 6, "map_winner": 1, "rank_1": 152, "rank_2": 74, "event_id": 3472, "match_id": 2318366}
{"event_timestamp": "2026-05-11 19:53:28", "date": "2017-12-24", "team_1": "Espada", "team_2": "EPG", "map": "Cache", "result_1": 16, "result_2": 10, "map_winner": 1, "rank_1": 152, "rank_2": 74, "event_id": 3472, "match_id": 2318366}
{"event_timestamp": "2026-05-11 19:53:28", "date": "2017-12-23", "team_1": "AGO", "team_2": "ALTERNATE aTTaX", "map": "Train", "result_1": 16, "result_2": 11, "map_winner": 1, "rank_1": 20, "rank_2": 39, "event_id": 3333, "match_id": 2318353}
{"event_timestamp": "2026-05-11 19:53:28", "date": "2017-12-23", "team_1": "Recca", "team_2": "BOOT-d[S]", "map": "Cobblestone", "result_1": 13, "result_2": 16, "map_winner": 2, "rank_1": 144, "rank_2": 106, "event_id": 3383, "match_id": 2318351}
{"event_timestamp": "2026-05-11 19:53:28", "date": "2017-12-23", "team_1": "Recca", "team_2": "BOOT-d[S]", "map": "Mirage", "result_1": 10, "result_2": 16, "map_winner": 2, "rank_1": 144, "rank_2": 106, "event_id": 3383, "match_id": 2318351}
{"event_timestamp": "2026-05-11 19:53:28", "date": "2017-12-23", "team_1": "Red Wolf", "team_2": "Eclipse", "map": "Mirage", "result_1": 8, "result_2": 16, "map_winner": 2, "rank_1": 150, "rank_2": 63, "event_id": 3383, "match_id": 2318352}
{"event_timestamp": "2026-05-11 19:53:28", "date": "2017-12-23", "team_1": "Red Wolf", "team_2": "Eclipse", "map": "Cobblestone", "result_1": 10, "result_2": 16, "map_winner": 2, "rank_1": 150, "rank_2": 63, "event_id": 3383, "match_id": 2318352}
{"event_timestamp": "2026-05-11 19:53:28", "date": "2017-12-23", "team_1": "Recca", "team_2": "Red Wolf", "map": "Mirage", "result_1": 16, "result_2": 6, "map_winner": 1, "rank_1": 144, "rank_2": 150, "event_id": 3383, "match_id": 2318357}
{"event_timestamp": "2026-05-11 19:53:28", "date": "2017-12-23", "team_1": "Recca", "team_2": "Red Wolf", "map": "Cobblestone", "result_1": 16, "result_2": 8, "map_winner": 1, "rank_1": 144, "rank_2": 150, "event_id": 3383, "match_id": 2318357}
{"event_timestamp": "2026-05-11 19:53:28", "date": "2017-12-23", "team_1": "BOOT-d[S]", "team_2": "Eclipse", "map": "Inferno", "result_1": 16, "result_2": 5, "map_winner": 1, "rank_1": 106, "rank_2": 63, "event_id": 3383, "match_id": 2318356}
{"event_timestamp": "2026-05-11 19:53:28", "date": "2017-12-23", "team_1": "BOOT-d[S]", "team_2": "Eclipse", "map": "Mirage", "result_1": 16, "result_2": 3, "map_winner": 1, "rank_1": 106, "rank_2": 63, "event_id": 3383, "match_id": 2318356}
{"event_timestamp": "2026-05-11 19:53:28", "date": "2017-12-23", "team_1": "Izako Boars", "team_2": "Squared", "map": "Mirage", "result_1": 16, "result_2": 12, "map_winner": 1, "rank_1": 243, "rank_2": 95, "event_id": 3464, "match_id": 2318354}
{"event_timestamp": "2026-05-11 19:53:28", "date": "2017-12-23", "team_1": "AGO", "team_2": "ALTERNATE aTTaX", "map": "Overpass", "result_1": 16, "result_2": 8, "map_winner": 1, "rank_1": 20, "rank_2": 39, "event_id": 3333, "match_id": 2318353}
{"event_timestamp": "2026-05-11 19:53:28", "date": "2017-12-23", "team_1": "mousesports", "team_2": "Nemiga", "map": "Mirage", "result_1": 14, "result_2": 16, "map_winner": 2, "rank_1": 9, "rank_2": 64, "event_id": 3421, "match_id": 2318307}
{"event_timestamp": "2026-05-11 19:53:28", "date": "2017-12-23", "team_1": "Valiance", "team_2": "HellRaisers", "map": "Mirage", "result_1": 16, "result_2": 12, "map_winner": 1, "rank_1": 37, "rank_2": 18, "event_id": 3421, "match_id": 2318335}
{"event_timestamp": "2026-05-11 19:53:28", "date": "2017-12-23", "team_1": "Izako Boars", "team_2": "Squared", "map": "Train", "result_1": 16, "result_2": 12, "map_winner": 1, "rank_1": 243, "rank_2": 95, "event_id": 3464, "match_id": 2318354}
{"event_timestamp": "2026-05-11 19:53:28", "date": "2017-12-23", "team_1": "Izako Boars", "team_2": "Squared", "map": "Nuke", "result_1": 5, "result_2": 16, "map_winner": 2, "rank_1": 243, "rank_2": 95, "event_id": 3464, "match_id": 2318354}
{"event_timestamp": "2026-05-11 19:53:28", "date": "2017-12-23", "team_1": "mousesports", "team_2": "Nemiga", "map": "Train", "result_1": 19, "result_2": 15, "map_winner": 1, "rank_1": 9, "rank_2": 64, "event_id": 3421, "match_id": 2318307}
{"event_timestamp": "2026-05-11 19:53:28", "date": "2017-12-23", "team_1": "mousesports", "team_2": "Nemiga", "map": "Cobblestone", "result_1": 16, "result_2": 8, "map_winner": 1, "rank_1": 9, "rank_2": 64, "event_id": 3421, "match_id": 2318307}
{"event_timestamp": "2026-05-11 19:53:28", "date": "2017-12-23", "team_1": "Valiance", "team_2": "HellRaisers", "map": "Inferno", "result_1": 16, "result_2": 8, "map_winner": 1, "rank_1": 37, "rank_2": 18, "event_id": 3421, "match_id": 2318335}
{"event_timestamp": "2026-05-11 19:53:28", "date": "2017-12-22", "team_1": "Heroic", "team_2": "Sprout", "map": "Mirage", "result_1": 16, "result_2": 10, "map_winner": 1, "rank_1": 19, "rank_2": 29, "event_id": 3421, "match_id": 2318315}
{"event_timestamp": "2026-05-11 19:53:28", "date": "2017-12-22", "team_1": "Isurus", "team_2": "FURIA", "map": "Inferno", "result_1": 16, "result_2": 8, "map_winner": 1, "rank_1": 183, "rank_2": 260, "event_id": 3465, "match_id": 2318320}
{"event_timestamp": "2026-05-11 19:53:28", "date": "2017-12-22", "team_1": "Isurus", "team_2": "FURIA", "map": "Overpass", "result_1": 13, "result_2": 16, "map_winner": 2, "rank_1": 183, "rank_2": 260, "event_id": 3465, "match_id": 2318320}
{"event_timestamp": "2026-05-11 19:53:28", "date": "2017-12-22", "team_1": "ViCi", "team_2": "BOOT-d[S]", "map": "Train", "result_1": 3, "result_2": 16, "map_winner": 2, "rank_1": 49, "rank_2": 106, "event_id": 3383, "match_id": 2318328}
{"event_timestamp": "2026-05-11 19:53:28", "date": "2017-12-22", "team_1": "ViCi", "team_2": "BOOT-d[S]", "map": "Mirage", "result_1": 6, "result_2": 16, "map_winner": 2, "rank_1": 49, "rank_2": 106, "event_id": 3383, "match_id": 2318328}
{"event_timestamp": "2026-05-11 19:53:28", "date": "2017-12-22", "team_1": "ViCi", "team_2": "BOOT-d[S]", "map": "Inferno", "result_1": 16, "result_2": 14, "map_winner": 1, "rank_1": 49, "rank_2": 106, "event_id": 3383, "match_id": 2318328}
{"event_timestamp": "2026-05-11 19:53:28", "date": "2017-12-22", "team_1": "Spirit", "team_2": "EPG", "map": "Inferno", "result_1": 16, "result_2": 10, "map_winner": 1, "rank_1": 40, "rank_2": 74, "event_id": 3449, "match_id": 2318308}
{"event_timestamp": "2026-05-11 19:53:28", "date": "2017-12-22", "team_1": "Spirit", "team_2": "EPG", "map": "Nuke", "result_1": 16, "result_2": 12, "map_winner": 1, "rank_1": 40, "rank_2": 74, "event_id": 3449, "match_id": 2318308}
{"event_timestamp": "2026-05-11 19:53:28", "date": "2017-12-22", "team_1": "eXtatus", "team_2": "ALTERNATE aTTaX", "map": "Train", "result_1": 13, "result_2": 16, "map_winner": 2, "rank_1": 44, "rank_2": 39, "event_id": 3333, "match_id": 2318316}
{"event_timestamp": "2026-05-11 19:53:28", "date": "2017-12-22", "team_1": "Isurus", "team_2": "FURIA", "map": "Mirage", "result_1": 16, "result_2": 4, "map_winner": 1, "rank_1": 183, "rank_2": 260, "event_id": 3465, "match_id": 2318320}
{"event_timestamp": "2026-05-11 19:53:28", "date": "2017-12-22", "team_1": "Heroic", "team_2": "Sprout", "map": "Cobblestone", "result_1": 16, "result_2": 14, "map_winner": 1, "rank_1": 19, "rank_2": 29, "event_id": 3421, "match_id": 2318315}
{"event_timestamp": "2026-05-11 19:53:28", "date": "2017-12-22", "team_1": "ALTERNATE aTTaX", "team_2": "Red Reserve", "map": "Mirage", "result_1": 5, "result_2": 16, "map_winner": 2, "rank_1": 39, "rank_2": 59, "event_id": 3461, "match_id": 2318350}
{"event_timestamp": "2026-05-11 19:53:28", "date": "2017-12-22", "team_1": "GameAgents", "team_2": "ALTERNATE aTTaX", "map": "Cobblestone", "result_1": 11, "result_2": 16, "map_winner": 2, "rank_1": 112, "rank_2": 39, "event_id": 3461, "match_id": 2318333}
{"event_timestamp": "2026-05-11 19:53:28", "date": "2017-12-22", "team_1": "Spirit", "team_2": "HAVU", "map": "Inferno", "result_1": 16, "result_2": 7, "map_winner": 1, "rank_1": 40, "rank_2": 57, "event_id": 3421, "match_id": 2318306}
{"event_timestamp": "2026-05-11 19:53:28", "date": "2017-12-22", "team_1": "Spirit", "team_2": "HAVU", "map": "Cache", "result_1": 16, "result_2": 10, "map_winner": 1, "rank_1": 40, "rank_2": 57, "event_id": 3421, "match_id": 2318306}
{"event_timestamp": "2026-05-11 19:53:28", "date": "2017-12-22", "team_1": "Spirit", "team_2": "HAVU", "map": "Nuke", "result_1": 14, "result_2": 16, "map_winner": 2, "rank_1": 40, "rank_2": 57, "event_id": 3421, "match_id": 2318306}
{"event_timestamp": "2026-05-11 19:53:28", "date": "2017-12-22", "team_1": "ALTERNATE aTTaX", "team_2": "Red Reserve", "map": "Cobblestone", "result_1": 4, "result_2": 16, "map_winner": 2, "rank_1": 39, "rank_2": 59, "event_id": 3461, "match_id": 2318350}
{"event_timestamp": "2026-05-11 19:53:28", "date": "2017-12-22", "team_1": "Windigo", "team_2": "Red Reserve", "map": "Overpass", "result_1": 12, "result_2": 16, "map_winner": 2, "rank_1": 43, "rank_2": 59, "event_id": 3461, "match_id": 2318334}
{"event_timestamp": "2026-05-11 19:53:28", "date": "2017-12-22", "team_1": "Windigo", "team_2": "Red Reserve", "map": "Cobblestone", "result_1": 8, "result_2": 16, "map_winner": 2, "rank_1": 43, "rank_2": 59, "event_id": 3461, "match_id": 2318334}
{"event_timestamp": "2026-05-11 19:53:28", "date": "2017-12-22", "team_1": "GameAgents", "team_2": "ALTERNATE aTTaX", "map": "Train", "result_1": 4, "result_2": 16, "map_winner": 2, "rank_1": 112, "rank_2": 39, "event_id": 3461, "match_id": 2318333}
{"event_timestamp": "2026-05-11 19:53:28", "date": "2017-12-21", "team_1": "MVP PK", "team_2": "Flash", "map": "Inferno", "result_1": 13, "result_2": 16, "map_winner": 2, "rank_1": 54, "rank_2": 56, "event_id": 3383, "match_id": 2318299}
{"event_timestamp": "2026-05-11 19:53:28", "date": "2017-12-21", "team_1": "ALTERNATE aTTaX", "team_2": "BRIEF", "map": "Cobblestone", "result_1": 16, "result_2": 7, "map_winner": 1, "rank_1": 39, "rank_2": 201, "event_id": 3461, "match_id": 2318294}
{"event_timestamp": "2026-05-11 19:53:28", "date": "2017-12-21", "team_1": "EURONICS", "team_2": "Red Reserve", "map": "Train", "result_1": 16, "result_2": 11, "map_winner": 1, "rank_1": 207, "rank_2": 59, "event_id": 3356, "match_id": 2318304}
{"event_timestamp": "2026-05-11 19:53:28", "date": "2017-12-21", "team_1": "MANS NOT HOT", "team_2": "GoodJob", "map": "Cache", "result_1": 16, "result_2": 6, "map_winner": 1, "rank_1": 60, "rank_2": 71, "event_id": 3457, "match_id": 2318325}
{"event_timestamp": "2026-05-11 19:53:28", "date": "2017-12-21", "team_1": "Nexus", "team_2": "Windigo", "map": "Train", "result_1": 3, "result_2": 16, "map_winner": 2, "rank_1": 41, "rank_2": 43, "event_id": 3382, "match_id": 2318314}
{"event_timestamp": "2026-05-11 19:53:28", "date": "2017-12-21", "team_1": "MANS NOT HOT", "team_2": "Espada", "map": "Train", "result_1": 16, "result_2": 5, "map_winner": 1, "rank_1": 60, "rank_2": 152, "event_id": 3457, "match_id": 2318267}
{"event_timestamp": "2026-05-11 19:53:28", "date": "2017-12-21", "team_1": "Izako Boars", "team_2": "PSYCHOACTIVE", "map": "Train", "result_1": 16, "result_2": 2, "map_winner": 1, "rank_1": 243, "rank_2": 300, "event_id": 3464, "match_id": 2318323}
{"event_timestamp": "2026-05-11 19:53:28", "date": "2017-12-21", "team_1": "INTZ", "team_2": "Isurus", "map": "Overpass", "result_1": 9, "result_2": 16, "map_winner": 2, "rank_1": 156, "rank_2": 183, "event_id": 3465, "match_id": 2318290}
{"event_timestamp": "2026-05-11 19:53:28", "date": "2017-12-21", "team_1": "TheMongolz", "team_2": "5POWER", "map": "Mirage", "result_1": 13, "result_2": 16, "map_winner": 2, "rank_1": 105, "rank_2": 72, "event_id": 3456, "match_id": 2318256}
{"event_timestamp": "2026-05-11 19:53:28", "date": "2017-12-21", "team_1": "SCARZ Absolute", "team_2": "Flash", "map": "Cobblestone", "result_1": 11, "result_2": 16, "map_winner": 2, "rank_1": 160, "rank_2": 56, "event_id": 3383, "match_id": 2318255}
{"event_timestamp": "2026-05-11 19:53:28", "date": "2017-12-21", "team_1": "Izako Boars", "team_2": "bruto500", "map": "Mirage", "result_1": 16, "result_2": 4, "map_winner": 1, "rank_1": 243, "rank_2": 331, "event_id": 3464, "match_id": 2318310}
{"event_timestamp": "2026-05-11 19:53:28", "date": "2017-12-21", "team_1": "INTZ", "team_2": "Isurus", "map": "Cobblestone", "result_1": 16, "result_2": 9, "map_winner": 1, "rank_1": 156, "rank_2": 183, "event_id": 3465, "match_id": 2318290}
{"event_timestamp": "2026-05-11 19:53:28", "date": "2017-12-21", "team_1": "Windigo", "team_2": "Movistar Riders", "map": "Overpass", "result_1": 16, "result_2": 13, "map_winner": 1, "rank_1": 43, "rank_2": 75, "event_id": 3461, "match_id": 2318295}
{"event_timestamp": "2026-05-11 19:53:28", "date": "2017-12-21", "team_1": "INTZ", "team_2": "Isurus", "map": "Inferno", "result_1": 5, "result_2": 16, "map_winner": 2, "rank_1": 156, "rank_2": 183, "event_id": 3465, "match_id": 2318290}
{"event_timestamp": "2026-05-11 19:53:28", "date": "2017-12-21", "team_1": "EN9MY", "team_2": "FURIA", "map": "Cache", "result_1": 5, "result_2": 16, "map_winner": 2, "rank_1": 249, "rank_2": 260, "event_id": 3465, "match_id": 2318291}
{"event_timestamp": "2026-05-11 19:53:28", "date": "2017-12-21", "team_1": "EN9MY", "team_2": "FURIA", "map": "Mirage", "result_1": 2, "result_2": 16, "map_winner": 2, "rank_1": 249, "rank_2": 260, "event_id": 3465, "match_id": 2318291}
{"event_timestamp": "2026-05-11 19:53:28", "date": "2017-12-21", "team_1": "Red Reserve", "team_2": "EURONICS", "map": "Overpass", "result_1": 14, "result_2": 16, "map_winner": 2, "rank_1": 59, "rank_2": 207, "event_id": 3356, "match_id": 2318305}
{"event_timestamp": "2026-05-11 19:53:28", "date": "2017-12-21", "team_1": "Nexus", "team_2": "Windigo", "map": "Mirage", "result_1": 14, "result_2": 16, "map_winner": 2, "rank_1": 41, "rank_2": 43, "event_id": 3382, "match_id": 2318314}
{"event_timestamp": "2026-05-11 19:53:28", "date": "2017-12-21", "team_1": "GameAgents", "team_2": "Refuse", "map": "Cache", "result_1": 16, "result_2": 5, "map_winner": 1, "rank_1": 112, "rank_2": 110, "event_id": 3458, "match_id": 2318247}
{"event_timestamp": "2026-05-11 19:53:28", "date": "2017-12-21", "team_1": "Vega Squadron", "team_2": "Tricked", "map": "Mirage", "result_1": 16, "result_2": 14, "map_winner": 1, "rank_1": 25, "rank_2": 58, "event_id": 3421, "match_id": 2318285}
{"event_timestamp": "2026-05-11 19:53:28", "date": "2017-12-21", "team_1": "GameAgents", "team_2": "Refuse", "map": "Overpass", "result_1": 7, "result_2": 16, "map_winner": 2, "rank_1": 112, "rank_2": 110, "event_id": 3458, "match_id": 2318247}
{"event_timestamp": "2026-05-11 19:53:28", "date": "2017-12-21", "team_1": "MANS NOT HOT", "team_2": "PRIDE", "map": "Mirage", "result_1": 8, "result_2": 16, "map_winner": 2, "rank_1": 60, "rank_2": 38, "event_id": 3418, "match_id": 2318319}
{"event_timestamp": "2026-05-11 19:53:28", "date": "2017-12-21", "team_1": "MANS NOT HOT", "team_2": "PRIDE", "map": "Cobblestone", "result_1": 16, "result_2": 14, "map_winner": 1, "rank_1": 60, "rank_2": 38, "event_id": 3418, "match_id": 2318319}
{"event_timestamp": "2026-05-11 19:53:28", "date": "2017-12-21", "team_1": "MANS NOT HOT", "team_2": "PRIDE", "map": "Train", "result_1": 7, "result_2": 16, "map_winner": 2, "rank_1": 60, "rank_2": 38, "event_id": 3418, "match_id": 2318319}
{"event_timestamp": "2026-05-11 19:53:28", "date": "2017-12-21", "team_1": "Movistar Riders", "team_2": "ALTERNATE aTTaX", "map": "Inferno", "result_1": 16, "result_2": 8, "map_winner": 1, "rank_1": 75, "rank_2": 39, "event_id": 3461, "match_id": 2318332}
{"event_timestamp": "2026-05-11 19:53:28", "date": "2017-12-21", "team_1": "Movistar Riders", "team_2": "ALTERNATE aTTaX", "map": "Overpass", "result_1": 6, "result_2": 16, "map_winner": 2, "rank_1": 75, "rank_2": 39, "event_id": 3461, "match_id": 2318332}
{"event_timestamp": "2026-05-11 19:53:28", "date": "2017-12-21", "team_1": "Vega Squadron", "team_2": "Tricked", "map": "Train", "result_1": 16, "result_2": 11, "map_winner": 1, "rank_1": 25, "rank_2": 58, "event_id": 3421, "match_id": 2318285}
{"event_timestamp": "2026-05-11 19:53:28", "date": "2017-12-21", "team_1": "Movistar Riders", "team_2": "ALTERNATE aTTaX", "map": "Mirage", "result_1": 6, "result_2": 16, "map_winner": 2, "rank_1": 75, "rank_2": 39, "event_id": 3461, "match_id": 2318332}
{"event_timestamp": "2026-05-11 19:53:28", "date": "2017-12-21", "team_1": "GoodJob", "team_2": "Espada", "map": "Inferno", "result_1": 16, "result_2": 11, "map_winner": 1, "rank_1": 71, "rank_2": 152, "event_id": 3457, "match_id": 2318327}
{"event_timestamp": "2026-05-11 19:53:28", "date": "2017-12-21", "team_1": "ALTERNATE aTTaX", "team_2": "Windigo", "map": "Cobblestone", "result_1": 9, "result_2": 16, "map_winner": 2, "rank_1": 39, "rank_2": 43, "event_id": 3461, "match_id": 2318329}
{"event_timestamp": "2026-05-11 19:53:28", "date": "2017-12-21", "team_1": "BRIEF", "team_2": "Movistar Riders", "map": "Inferno", "result_1": 10, "result_2": 16, "map_winner": 2, "rank_1": 201, "rank_2": 75, "event_id": 3461, "match_id": 2318330}
{"event_timestamp": "2026-05-11 19:53:28", "date": "2017-12-21", "team_1": "AGO", "team_2": "eXtatus", "map": "Mirage", "result_1": 16, "result_2": 13, "map_winner": 1, "rank_1": 20, "rank_2": 44, "event_id": 3421, "match_id": 2318284}
{"event_timestamp": "2026-05-11 19:53:28", "date": "2017-12-21", "team_1": "AGO", "team_2": "eXtatus", "map": "Cobblestone", "result_1": 6, "result_2": 16, "map_winner": 2, "rank_1": 20, "rank_2": 44, "event_id": 3421, "match_id": 2318284}
{"event_timestamp": "2026-05-11 19:53:28", "date": "2017-12-21", "team_1": "AGO", "team_2": "eXtatus", "map": "Cache", "result_1": 19, "result_2": 15, "map_winner": 1, "rank_1": 20, "rank_2": 44, "event_id": 3421, "match_id": 2318284}
{"event_timestamp": "2026-05-11 19:53:28", "date": "2017-12-21", "team_1": "GoodJob", "team_2": "Espada", "map": "Overpass", "result_1": 16, "result_2": 14, "map_winner": 1, "rank_1": 71, "rank_2": 152, "event_id": 3457, "match_id": 2318327}
{"event_timestamp": "2026-05-11 19:53:28", "date": "2017-12-21", "team_1": "GameAgents", "team_2": "Refuse", "map": "Cobblestone", "result_1": 16, "result_2": 8, "map_winner": 1, "rank_1": 112, "rank_2": 110, "event_id": 3458, "match_id": 2318247}
{"event_timestamp": "2026-05-11 19:53:28", "date": "2017-12-20", "team_1": "Nexus", "team_2": "pro100", "map": "Mirage", "result_1": 13, "result_2": 16, "map_winner": 2, "rank_1": 41, "rank_2": 47, "event_id": 3382, "match_id": 2318269}
{"event_timestamp": "2026-05-11 19:53:28", "date": "2017-12-20", "team_1": "Red Reserve", "team_2": "HAVU", "map": "Mirage", "result_1": 13, "result_2": 16, "map_winner": 2, "rank_1": 59, "rank_2": 57, "event_id": 3421, "match_id": 2318283}
{"event_timestamp": "2026-05-11 19:53:28", "date": "2017-12-20", "team_1": "Red Reserve", "team_2": "HAVU", "map": "Inferno", "result_1": 19, "result_2": 17, "map_winner": 1, "rank_1": 59, "rank_2": 57, "event_id": 3421, "match_id": 2318283}
{"event_timestamp": "2026-05-11 19:53:28", "date": "2017-12-20", "team_1": "Nexus", "team_2": "pro100", "map": "Cobblestone", "result_1": 16, "result_2": 9, "map_winner": 1, "rank_1": 41, "rank_2": 47, "event_id": 3382, "match_id": 2318269}